Workbook
Name Credibility_Z: Indication!$C$14
Name Full_Credibility_Units: Indication!$C$10
Name Planning_Factor: Indication!$C$16
Name Selected_Loss_Ratio: Indication!$C$15
Name Target_Loss_Ratio: Indication!$C$9

Sheet Indication
A1: 2027 planning indication | Linn County corn RP
A2: Frozen RMA experience through commodity year 2024 · reinsured buyup scope · nominal dollars
A3: Selected loss ratio | D3: Credibility Z | G3: Planning factor | J3: 2024 base premium | M3: Planning premium
A4: =C15 -> 0.88882582 | D4: =C14 -> 0.53150729 | G4: =C16 -> 1.3674243 | J4: =C17 -> 6008122 | M4: =C18 -> 8215652.3
A7: Selection bridge | H7: Sensitivity | planning factor
A8: Assumption | B8: Basis | C8: Value | H8: Target / Z | I8: 0 | J8: 0.25 | K8: 0.5 | L8: 0.75 | M8: 1
A9: Target loss ratio | B9: Portfolio planning target | C9: 0.65 | H9: 0.6 | I9: =(I$8*$C$11+(1-I$8)*$C$12)/$H9 -> 0.82560762 | J9: =(J$8*$C$11+(1-J$8)*$C$12)/$H9 -> 1.1340553 | K9: =(K$8*$C$11+(1-K$8)*$C$12)/$H9 -> 1.442503 | L9: =(L$8*$C$11+(1-L$8)*$C$12)/$H9 -> 1.7509506 | M9: =(M$8*$C$11+(1-M$8)*$C$12)/$H9 -> 2.0593983
A10: Full credibility | B10: Units earning premium | C10: 40000 | H10: 0.65 | I10: =(I$8*$C$11+(1-I$8)*$C$12)/$H10 -> 0.76209934 | J10: =(J$8*$C$11+(1-J$8)*$C$12)/$H10 -> 1.0468203 | K10: =(K$8*$C$11+(1-K$8)*$C$12)/$H10 -> 1.3315412 | L10: =(L$8*$C$11+(1-L$8)*$C$12)/$H10 -> 1.6162621 | M10: =(M$8*$C$11+(1-M$8)*$C$12)/$H10 -> 1.9009831
A11: Linn horizon selection | B11: 20% / 30% / 50% | C11: =Annual_Experience!G21 -> 1.235639 | H11: 0.7 | I11: =(I$8*$C$11+(1-I$8)*$C$12)/$H11 -> 0.70766367 | J11: =(J$8*$C$11+(1-J$8)*$C$12)/$H11 -> 0.97204739 | K11: =(K$8*$C$11+(1-K$8)*$C$12)/$H11 -> 1.2364311 | L11: =(L$8*$C$11+(1-L$8)*$C$12)/$H11 -> 1.5008148 | M11: =(M$8*$C$11+(1-M$8)*$C$12)/$H11 -> 1.7651986
A12: Iowa ex-Linn horizon selection | B12: 20% / 30% / 50% | C12: =Annual_Experience!J21 -> 0.49536457
A13: Linn decade earned units | B13: 2015–2024 | C13: =SUM(Annual_Experience!G4:G13) -> 11300 | H13: How to read it
A14: Credibility Z | B14: MIN(1, SQRT(units / 40,000)) | C14: =MIN(1,SQRT(C13/C10)) -> 0.53150729 | H14: The matrix isolates the judgment in the credibility and target assumptions. Because Linn's weighted experience exceeds the complement's, the factor rises as Z increases; at any Z, raising the target from 60% to 70% lowers the factor. At the 65% target, the range is 0.762x to 1.901x, and the portfolio standard Z of 53.2% produces 1.367x. A reasonable change in credibility can move the indication across 1.0x, so the selection is not mechanically precise.
A15: Selected loss ratio | B15: Z × Linn + (1−Z) × complement | C15: =C14*C11+(1-C14)*C12 -> 0.88882582
A16: Planning factor | B16: Selected loss ratio / target | C16: =C15/C9 -> 1.3674243
A17: Linn 2024 base premium | B17: Total Premium field | C17: =Annual_Experience!C13 -> 6008122
A18: Indicated planning premium | B18: 2024 base premium × factor | C18: =C17*C16 -> 8215652.3
A19: Dollar change | B19: Planning minus 2024 base | C19: =C18-C17 -> 2207530.3
A20: Percent change | B20: Dollar change / 2024 base | C20: =C19/C17 -> 0.36742435
A23: Actuarial reading
A24: The Linn result is episodic rather than a steady deterioration. Commodity years 2020 and 2023 produced 91.4% of the decade’s indemnity on 20.3% of its base premium; their loss ratios were 493.2% and 414.4%. That concentration lifts Linn’s 3-year, 5-year, and 10-year loss ratios to 136.8%, 157.2%, and 98.0%, compared with 54.0%, 55.3%, and 44.3% for Iowa ex-Linn. The recency weighting gives Linn 123.6% and the complement 49.5%; 53.2% credibility selects 88.9%, implying a 1.367x planning factor and $8,215,652 on Linn’s $6,008,122 2024 base premium. The factor is a signal to examine pricing adequacy, not a claim about why either outlier occurred.
A30: Use boundary
A31: RMA Summary of Business records are aggregated by geography, commodity, plan, and coverage level. They contain no policy or claim identifiers and cannot support policy-level or claim-level inference. Amounts are nominal, and Total Premium is base premium before subsidies. This workbook does not model expenses, reinsurance, taxes, profit, trend, mix shifts, or operational changes. The result is a planning indication only, not a filed rate, complete premium need, reserve estimate, or individual underwriting action.
A36: Annual experience | C36: Coverage experience | E36: Controls | G36: Sources & definitions | I36: Filtered detail

Sheet Annual_Experience
A1: Annual experience | Linn County corn RP
A2: Commodity years 2015–2024 · Iowa complement excludes Linn · all ratios recomputed from summed components
A3: Commodity Year | B3: Linn Liability | C3: Linn Base Premium | D3: Linn Indemnity | E3: Linn Policies Earning | F3: Linn Policies Indemnified | G3: Linn Units Earning | H3: Linn Units Indemnified | I3: Linn Acres | J3: Linn Loss Ratio | K3: Linn Rate on Liability | L3: Linn Policy Claim Frequency | M3: Linn Severity | O3: Iowa ex-Linn Liability | P3: Iowa ex-Linn Base Premium | Q3: Iowa ex-Linn Indemnity | R3: Iowa ex-Linn Policies Earning | S3: Iowa ex-Linn Policies Indemnified | T3: Iowa ex-Linn Units Earning | U3: Iowa ex-Linn Units Indemnified | V3: Iowa ex-Linn Acres | W3: Iowa ex-Linn Loss Ratio | X3: Iowa ex-Linn Rate on Liability | Y3: Iowa ex-Linn Policy Claim Frequency | Z3: Iowa ex-Linn Severity
A4: 2015 | B4: =SUMIFS(Source_Detail!$V$2:$V$6492,Source_Detail!$B$2:$B$6492,$A4,Source_Detail!$AD$2:$AD$6492,"Linn") -> 87239005 | C4: =SUMIFS(Source_Detail!$W$2:$W$6492,Source_Detail!$B$2:$B$6492,$A4,Source_Detail!$AD$2:$AD$6492,"Linn") -> 4665066 | D4: =SUMIFS(Source_Detail!$AB$2:$AB$6492,Source_Detail!$B$2:$B$6492,$A4,Source_Detail!$AD$2:$AD$6492,"Linn") -> 521357 | E4: =SUMIFS(Source_Detail!$O$2:$O$6492,Source_Detail!$B$2:$B$6492,$A4,Source_Detail!$AD$2:$AD$6492,"Linn") -> 777 | F4: =SUMIFS(Source_Detail!$P$2:$P$6492,Source_Detail!$B$2:$B$6492,$A4,Source_Detail!$AD$2:$AD$6492,"Linn") -> 78 | G4: =SUMIFS(Source_Detail!$Q$2:$Q$6492,Source_Detail!$B$2:$B$6492,$A4,Source_Detail!$AD$2:$AD$6492,"Linn") -> 1215 | H4: =SUMIFS(Source_Detail!$R$2:$R$6492,Source_Detail!$B$2:$B$6492,$A4,Source_Detail!$AD$2:$AD$6492,"Linn") -> 110 | I4: =SUMIFS(Source_Detail!$T$2:$T$6492,Source_Detail!$B$2:$B$6492,$A4,Source_Detail!$AD$2:$AD$6492,"Linn") -> 139732 | J4: =IFERROR(D4/C4,"N/M") -> 0.11175769 | K4: =IFERROR(C4/B4,"N/M") -> 0.053474544 | L4: =IFERROR(F4/E4,"N/M") -> 0.1003861 | M4: =IFERROR(D4/F4,"N/M") -> 6684.0641 | O4: =SUMIFS(Source_Detail!$V$2:$V$6492,Source_Detail!$B$2:$B$6492,$A4,Source_Detail!$AD$2:$AD$6492,"Iowa ex-Linn") -> 7467198121 | P4: =SUMIFS(Source_Detail!$W$2:$W$6492,Source_Detail!$B$2:$B$6492,$A4,Source_Detail!$AD$2:$AD$6492,"Iowa ex-Linn") -> 475456680 | Q4: =SUMIFS(Source_Detail!$AB$2:$AB$6492,Source_Detail!$B$2:$B$6492,$A4,Source_Detail!$AD$2:$AD$6492,"Iowa ex-Linn") -> 89858710 | R4: =SUMIFS(Source_Detail!$O$2:$O$6492,Source_Detail!$B$2:$B$6492,$A4,Source_Detail!$AD$2:$AD$6492,"Iowa ex-Linn") -> 61356 | S4: =SUMIFS(Source_Detail!$P$2:$P$6492,Source_Detail!$B$2:$B$6492,$A4,Source_Detail!$AD$2:$AD$6492,"Iowa ex-Linn") -> 6148 | T4: =SUMIFS(Source_Detail!$Q$2:$Q$6492,Source_Detail!$B$2:$B$6492,$A4,Source_Detail!$AD$2:$AD$6492,"Iowa ex-Linn") -> 102824 | U4: =SUMIFS(Source_Detail!$R$2:$R$6492,Source_Detail!$B$2:$B$6492,$A4,Source_Detail!$AD$2:$AD$6492,"Iowa ex-Linn") -> 8474 | V4: =SUMIFS(Source_Detail!$T$2:$T$6492,Source_Detail!$B$2:$B$6492,$A4,Source_Detail!$AD$2:$AD$6492,"Iowa ex-Linn") -> 12072155 | W4: =IFERROR(Q4/P4,"N/M") -> 0.18899453 | X4: =IFERROR(P4/O4,"N/M") -> 0.063672702 | Y4: =IFERROR(S4/R4,"N/M") -> 0.1002021 | Z4: =IFERROR(Q4/S4,"N/M") -> 14615.926
A5: 2016 | B5: =SUMIFS(Source_Detail!$V$2:$V$6492,Source_Detail!$B$2:$B$6492,$A5,Source_Detail!$AD$2:$AD$6492,"Linn") -> 83433406 | C5: =SUMIFS(Source_Detail!$W$2:$W$6492,Source_Detail!$B$2:$B$6492,$A5,Source_Detail!$AD$2:$AD$6492,"Linn") -> 3737568 | D5: =SUMIFS(Source_Detail!$AB$2:$AB$6492,Source_Detail!$B$2:$B$6492,$A5,Source_Detail!$AD$2:$AD$6492,"Linn") -> 145923 | E5: =SUMIFS(Source_Detail!$O$2:$O$6492,Source_Detail!$B$2:$B$6492,$A5,Source_Detail!$AD$2:$AD$6492,"Linn") -> 751 | F5: =SUMIFS(Source_Detail!$P$2:$P$6492,Source_Detail!$B$2:$B$6492,$A5,Source_Detail!$AD$2:$AD$6492,"Linn") -> 21 | G5: =SUMIFS(Source_Detail!$Q$2:$Q$6492,Source_Detail!$B$2:$B$6492,$A5,Source_Detail!$AD$2:$AD$6492,"Linn") -> 1166 | H5: =SUMIFS(Source_Detail!$R$2:$R$6492,Source_Detail!$B$2:$B$6492,$A5,Source_Detail!$AD$2:$AD$6492,"Linn") -> 27 | I5: =SUMIFS(Source_Detail!$T$2:$T$6492,Source_Detail!$B$2:$B$6492,$A5,Source_Detail!$AD$2:$AD$6492,"Linn") -> 141838 | J5: =IFERROR(D5/C5,"N/M") -> 0.039042233 | K5: =IFERROR(C5/B5,"N/M") -> 0.044797021 | L5: =IFERROR(F5/E5,"N/M") -> 0.027962716 | M5: =IFERROR(D5/F5,"N/M") -> 6948.7143 | O5: =SUMIFS(Source_Detail!$V$2:$V$6492,Source_Detail!$B$2:$B$6492,$A5,Source_Detail!$AD$2:$AD$6492,"Iowa ex-Linn") -> 7097400490 | P5: =SUMIFS(Source_Detail!$W$2:$W$6492,Source_Detail!$B$2:$B$6492,$A5,Source_Detail!$AD$2:$AD$6492,"Iowa ex-Linn") -> 398180956 | Q5: =SUMIFS(Source_Detail!$AB$2:$AB$6492,Source_Detail!$B$2:$B$6492,$A5,Source_Detail!$AD$2:$AD$6492,"Iowa ex-Linn") -> 38548089 | R5: =SUMIFS(Source_Detail!$O$2:$O$6492,Source_Detail!$B$2:$B$6492,$A5,Source_Detail!$AD$2:$AD$6492,"Iowa ex-Linn") -> 60086 | S5: =SUMIFS(Source_Detail!$P$2:$P$6492,Source_Detail!$B$2:$B$6492,$A5,Source_Detail!$AD$2:$AD$6492,"Iowa ex-Linn") -> 5210 | T5: =SUMIFS(Source_Detail!$Q$2:$Q$6492,Source_Detail!$B$2:$B$6492,$A5,Source_Detail!$AD$2:$AD$6492,"Iowa ex-Linn") -> 100970 | U5: =SUMIFS(Source_Detail!$R$2:$R$6492,Source_Detail!$B$2:$B$6492,$A5,Source_Detail!$AD$2:$AD$6492,"Iowa ex-Linn") -> 7139 | V5: =SUMIFS(Source_Detail!$T$2:$T$6492,Source_Detail!$B$2:$B$6492,$A5,Source_Detail!$AD$2:$AD$6492,"Iowa ex-Linn") -> 12199183 | W5: =IFERROR(Q5/P5,"N/M") -> 0.096810479 | X5: =IFERROR(P5/O5,"N/M") -> 0.056102365 | Y5: =IFERROR(S5/R5,"N/M") -> 0.08670905 | Z5: =IFERROR(Q5/S5,"N/M") -> 7398.8655
A6: 2017 | B6: =SUMIFS(Source_Detail!$V$2:$V$6492,Source_Detail!$B$2:$B$6492,$A6,Source_Detail!$AD$2:$AD$6492,"Linn") -> 85156216 | C6: =SUMIFS(Source_Detail!$W$2:$W$6492,Source_Detail!$B$2:$B$6492,$A6,Source_Detail!$AD$2:$AD$6492,"Linn") -> 4148028 | D6: =SUMIFS(Source_Detail!$AB$2:$AB$6492,Source_Detail!$B$2:$B$6492,$A6,Source_Detail!$AD$2:$AD$6492,"Linn") -> 153803 | E6: =SUMIFS(Source_Detail!$O$2:$O$6492,Source_Detail!$B$2:$B$6492,$A6,Source_Detail!$AD$2:$AD$6492,"Linn") -> 739 | F6: =SUMIFS(Source_Detail!$P$2:$P$6492,Source_Detail!$B$2:$B$6492,$A6,Source_Detail!$AD$2:$AD$6492,"Linn") -> 16 | G6: =SUMIFS(Source_Detail!$Q$2:$Q$6492,Source_Detail!$B$2:$B$6492,$A6,Source_Detail!$AD$2:$AD$6492,"Linn") -> 1117 | H6: =SUMIFS(Source_Detail!$R$2:$R$6492,Source_Detail!$B$2:$B$6492,$A6,Source_Detail!$AD$2:$AD$6492,"Linn") -> 17 | I6: =SUMIFS(Source_Detail!$T$2:$T$6492,Source_Detail!$B$2:$B$6492,$A6,Source_Detail!$AD$2:$AD$6492,"Linn") -> 138651 | J6: =IFERROR(D6/C6,"N/M") -> 0.037078583 | K6: =IFERROR(C6/B6,"N/M") -> 0.048710807 | L6: =IFERROR(F6/E6,"N/M") -> 0.02165088 | M6: =IFERROR(D6/F6,"N/M") -> 9612.6875 | O6: =SUMIFS(Source_Detail!$V$2:$V$6492,Source_Detail!$B$2:$B$6492,$A6,Source_Detail!$AD$2:$AD$6492,"Iowa ex-Linn") -> 7147544939 | P6: =SUMIFS(Source_Detail!$W$2:$W$6492,Source_Detail!$B$2:$B$6492,$A6,Source_Detail!$AD$2:$AD$6492,"Iowa ex-Linn") -> 424393346 | Q6: =SUMIFS(Source_Detail!$AB$2:$AB$6492,Source_Detail!$B$2:$B$6492,$A6,Source_Detail!$AD$2:$AD$6492,"Iowa ex-Linn") -> 109400203 | R6: =SUMIFS(Source_Detail!$O$2:$O$6492,Source_Detail!$B$2:$B$6492,$A6,Source_Detail!$AD$2:$AD$6492,"Iowa ex-Linn") -> 58722 | S6: =SUMIFS(Source_Detail!$P$2:$P$6492,Source_Detail!$B$2:$B$6492,$A6,Source_Detail!$AD$2:$AD$6492,"Iowa ex-Linn") -> 8553 | T6: =SUMIFS(Source_Detail!$Q$2:$Q$6492,Source_Detail!$B$2:$B$6492,$A6,Source_Detail!$AD$2:$AD$6492,"Iowa ex-Linn") -> 95832 | U6: =SUMIFS(Source_Detail!$R$2:$R$6492,Source_Detail!$B$2:$B$6492,$A6,Source_Detail!$AD$2:$AD$6492,"Iowa ex-Linn") -> 12167 | V6: =SUMIFS(Source_Detail!$T$2:$T$6492,Source_Detail!$B$2:$B$6492,$A6,Source_Detail!$AD$2:$AD$6492,"Iowa ex-Linn") -> 11731776 | W6: =IFERROR(Q6/P6,"N/M") -> 0.2577802 | X6: =IFERROR(P6/O6,"N/M") -> 0.0593761 | Y6: =IFERROR(S6/R6,"N/M") -> 0.1456524 | Z6: =IFERROR(Q6/S6,"N/M") -> 12790.857
A7: 2018 | B7: =SUMIFS(Source_Detail!$V$2:$V$6492,Source_Detail!$B$2:$B$6492,$A7,Source_Detail!$AD$2:$AD$6492,"Linn") -> 86540958 | C7: =SUMIFS(Source_Detail!$W$2:$W$6492,Source_Detail!$B$2:$B$6492,$A7,Source_Detail!$AD$2:$AD$6492,"Linn") -> 3442511 | D7: =SUMIFS(Source_Detail!$AB$2:$AB$6492,Source_Detail!$B$2:$B$6492,$A7,Source_Detail!$AD$2:$AD$6492,"Linn") -> 137627 | E7: =SUMIFS(Source_Detail!$O$2:$O$6492,Source_Detail!$B$2:$B$6492,$A7,Source_Detail!$AD$2:$AD$6492,"Linn") -> 724 | F7: =SUMIFS(Source_Detail!$P$2:$P$6492,Source_Detail!$B$2:$B$6492,$A7,Source_Detail!$AD$2:$AD$6492,"Linn") -> 16 | G7: =SUMIFS(Source_Detail!$Q$2:$Q$6492,Source_Detail!$B$2:$B$6492,$A7,Source_Detail!$AD$2:$AD$6492,"Linn") -> 1121 | H7: =SUMIFS(Source_Detail!$R$2:$R$6492,Source_Detail!$B$2:$B$6492,$A7,Source_Detail!$AD$2:$AD$6492,"Linn") -> 18 | I7: =SUMIFS(Source_Detail!$T$2:$T$6492,Source_Detail!$B$2:$B$6492,$A7,Source_Detail!$AD$2:$AD$6492,"Linn") -> 136981 | J7: =IFERROR(D7/C7,"N/M") -> 0.039978667 | K7: =IFERROR(C7/B7,"N/M") -> 0.03977898 | L7: =IFERROR(F7/E7,"N/M") -> 0.022099448 | M7: =IFERROR(D7/F7,"N/M") -> 8601.6875 | O7: =SUMIFS(Source_Detail!$V$2:$V$6492,Source_Detail!$B$2:$B$6492,$A7,Source_Detail!$AD$2:$AD$6492,"Iowa ex-Linn") -> 7210555930 | P7: =SUMIFS(Source_Detail!$W$2:$W$6492,Source_Detail!$B$2:$B$6492,$A7,Source_Detail!$AD$2:$AD$6492,"Iowa ex-Linn") -> 370485950 | Q7: =SUMIFS(Source_Detail!$AB$2:$AB$6492,Source_Detail!$B$2:$B$6492,$A7,Source_Detail!$AD$2:$AD$6492,"Iowa ex-Linn") -> 162615642 | R7: =SUMIFS(Source_Detail!$O$2:$O$6492,Source_Detail!$B$2:$B$6492,$A7,Source_Detail!$AD$2:$AD$6492,"Iowa ex-Linn") -> 57898 | S7: =SUMIFS(Source_Detail!$P$2:$P$6492,Source_Detail!$B$2:$B$6492,$A7,Source_Detail!$AD$2:$AD$6492,"Iowa ex-Linn") -> 10676 | T7: =SUMIFS(Source_Detail!$Q$2:$Q$6492,Source_Detail!$B$2:$B$6492,$A7,Source_Detail!$AD$2:$AD$6492,"Iowa ex-Linn") -> 94750 | U7: =SUMIFS(Source_Detail!$R$2:$R$6492,Source_Detail!$B$2:$B$6492,$A7,Source_Detail!$AD$2:$AD$6492,"Iowa ex-Linn") -> 15187 | V7: =SUMIFS(Source_Detail!$T$2:$T$6492,Source_Detail!$B$2:$B$6492,$A7,Source_Detail!$AD$2:$AD$6492,"Iowa ex-Linn") -> 11639546 | W7: =IFERROR(Q7/P7,"N/M") -> 0.43892526 | X7: =IFERROR(P7/O7,"N/M") -> 0.051381052 | Y7: =IFERROR(S7/R7,"N/M") -> 0.18439324 | Z7: =IFERROR(Q7/S7,"N/M") -> 15231.889
A8: 2019 | B8: =SUMIFS(Source_Detail!$V$2:$V$6492,Source_Detail!$B$2:$B$6492,$A8,Source_Detail!$AD$2:$AD$6492,"Linn") -> 90391166 | C8: =SUMIFS(Source_Detail!$W$2:$W$6492,Source_Detail!$B$2:$B$6492,$A8,Source_Detail!$AD$2:$AD$6492,"Linn") -> 3571761 | D8: =SUMIFS(Source_Detail!$AB$2:$AB$6492,Source_Detail!$B$2:$B$6492,$A8,Source_Detail!$AD$2:$AD$6492,"Linn") -> 860423 | E8: =SUMIFS(Source_Detail!$O$2:$O$6492,Source_Detail!$B$2:$B$6492,$A8,Source_Detail!$AD$2:$AD$6492,"Linn") -> 717 | F8: =SUMIFS(Source_Detail!$P$2:$P$6492,Source_Detail!$B$2:$B$6492,$A8,Source_Detail!$AD$2:$AD$6492,"Linn") -> 86 | G8: =SUMIFS(Source_Detail!$Q$2:$Q$6492,Source_Detail!$B$2:$B$6492,$A8,Source_Detail!$AD$2:$AD$6492,"Linn") -> 1082 | H8: =SUMIFS(Source_Detail!$R$2:$R$6492,Source_Detail!$B$2:$B$6492,$A8,Source_Detail!$AD$2:$AD$6492,"Linn") -> 109 | I8: =SUMIFS(Source_Detail!$T$2:$T$6492,Source_Detail!$B$2:$B$6492,$A8,Source_Detail!$AD$2:$AD$6492,"Linn") -> 139232 | J8: =IFERROR(D8/C8,"N/M") -> 0.24089602 | K8: =IFERROR(C8/B8,"N/M") -> 0.039514492 | L8: =IFERROR(F8/E8,"N/M") -> 0.11994421 | M8: =IFERROR(D8/F8,"N/M") -> 10004.919 | O8: =SUMIFS(Source_Detail!$V$2:$V$6492,Source_Detail!$B$2:$B$6492,$A8,Source_Detail!$AD$2:$AD$6492,"Iowa ex-Linn") -> 7669502022 | P8: =SUMIFS(Source_Detail!$W$2:$W$6492,Source_Detail!$B$2:$B$6492,$A8,Source_Detail!$AD$2:$AD$6492,"Iowa ex-Linn") -> 406226733 | Q8: =SUMIFS(Source_Detail!$AB$2:$AB$6492,Source_Detail!$B$2:$B$6492,$A8,Source_Detail!$AD$2:$AD$6492,"Iowa ex-Linn") -> 192506755 | R8: =SUMIFS(Source_Detail!$O$2:$O$6492,Source_Detail!$B$2:$B$6492,$A8,Source_Detail!$AD$2:$AD$6492,"Iowa ex-Linn") -> 57484 | S8: =SUMIFS(Source_Detail!$P$2:$P$6492,Source_Detail!$B$2:$B$6492,$A8,Source_Detail!$AD$2:$AD$6492,"Iowa ex-Linn") -> 11760 | T8: =SUMIFS(Source_Detail!$Q$2:$Q$6492,Source_Detail!$B$2:$B$6492,$A8,Source_Detail!$AD$2:$AD$6492,"Iowa ex-Linn") -> 95257 | U8: =SUMIFS(Source_Detail!$R$2:$R$6492,Source_Detail!$B$2:$B$6492,$A8,Source_Detail!$AD$2:$AD$6492,"Iowa ex-Linn") -> 16493 | V8: =SUMIFS(Source_Detail!$T$2:$T$6492,Source_Detail!$B$2:$B$6492,$A8,Source_Detail!$AD$2:$AD$6492,"Iowa ex-Linn") -> 12196687 | W8: =IFERROR(Q8/P8,"N/M") -> 0.47388992 | X8: =IFERROR(P8/O8,"N/M") -> 0.052966507 | Y8: =IFERROR(S8/R8,"N/M") -> 0.20457867 | Z8: =IFERROR(Q8/S8,"N/M") -> 16369.622
A9: 2020 | B9: =SUMIFS(Source_Detail!$V$2:$V$6492,Source_Detail!$B$2:$B$6492,$A9,Source_Detail!$AD$2:$AD$6492,"Linn") -> 90408678 | C9: =SUMIFS(Source_Detail!$W$2:$W$6492,Source_Detail!$B$2:$B$6492,$A9,Source_Detail!$AD$2:$AD$6492,"Linn") -> 3438536 | D9: =SUMIFS(Source_Detail!$AB$2:$AB$6492,Source_Detail!$B$2:$B$6492,$A9,Source_Detail!$AD$2:$AD$6492,"Linn") -> 16960242 | E9: =SUMIFS(Source_Detail!$O$2:$O$6492,Source_Detail!$B$2:$B$6492,$A9,Source_Detail!$AD$2:$AD$6492,"Linn") -> 702 | F9: =SUMIFS(Source_Detail!$P$2:$P$6492,Source_Detail!$B$2:$B$6492,$A9,Source_Detail!$AD$2:$AD$6492,"Linn") -> 438 | G9: =SUMIFS(Source_Detail!$Q$2:$Q$6492,Source_Detail!$B$2:$B$6492,$A9,Source_Detail!$AD$2:$AD$6492,"Linn") -> 1108 | H9: =SUMIFS(Source_Detail!$R$2:$R$6492,Source_Detail!$B$2:$B$6492,$A9,Source_Detail!$AD$2:$AD$6492,"Linn") -> 667 | I9: =SUMIFS(Source_Detail!$T$2:$T$6492,Source_Detail!$B$2:$B$6492,$A9,Source_Detail!$AD$2:$AD$6492,"Linn") -> 139913 | J9: =IFERROR(D9/C9,"N/M") -> 4.932402 | K9: =IFERROR(C9/B9,"N/M") -> 0.038033252 | L9: =IFERROR(F9/E9,"N/M") -> 0.62393162 | M9: =IFERROR(D9/F9,"N/M") -> 38722.014 | O9: =SUMIFS(Source_Detail!$V$2:$V$6492,Source_Detail!$B$2:$B$6492,$A9,Source_Detail!$AD$2:$AD$6492,"Iowa ex-Linn") -> 7608191067 | P9: =SUMIFS(Source_Detail!$W$2:$W$6492,Source_Detail!$B$2:$B$6492,$A9,Source_Detail!$AD$2:$AD$6492,"Iowa ex-Linn") -> 377435451 | Q9: =SUMIFS(Source_Detail!$AB$2:$AB$6492,Source_Detail!$B$2:$B$6492,$A9,Source_Detail!$AD$2:$AD$6492,"Iowa ex-Linn") -> 488635677 | R9: =SUMIFS(Source_Detail!$O$2:$O$6492,Source_Detail!$B$2:$B$6492,$A9,Source_Detail!$AD$2:$AD$6492,"Iowa ex-Linn") -> 56752 | S9: =SUMIFS(Source_Detail!$P$2:$P$6492,Source_Detail!$B$2:$B$6492,$A9,Source_Detail!$AD$2:$AD$6492,"Iowa ex-Linn") -> 16364 | T9: =SUMIFS(Source_Detail!$Q$2:$Q$6492,Source_Detail!$B$2:$B$6492,$A9,Source_Detail!$AD$2:$AD$6492,"Iowa ex-Linn") -> 94196 | U9: =SUMIFS(Source_Detail!$R$2:$R$6492,Source_Detail!$B$2:$B$6492,$A9,Source_Detail!$AD$2:$AD$6492,"Iowa ex-Linn") -> 24519 | V9: =SUMIFS(Source_Detail!$T$2:$T$6492,Source_Detail!$B$2:$B$6492,$A9,Source_Detail!$AD$2:$AD$6492,"Iowa ex-Linn") -> 12138719 | W9: =IFERROR(Q9/P9,"N/M") -> 1.2946205 | X9: =IFERROR(P9/O9,"N/M") -> 0.049609092 | Y9: =IFERROR(S9/R9,"N/M") -> 0.28834226 | Z9: =IFERROR(Q9/S9,"N/M") -> 29860.406
A10: 2021 | B10: =SUMIFS(Source_Detail!$V$2:$V$6492,Source_Detail!$B$2:$B$6492,$A10,Source_Detail!$AD$2:$AD$6492,"Linn") -> 100290881 | C10: =SUMIFS(Source_Detail!$W$2:$W$6492,Source_Detail!$B$2:$B$6492,$A10,Source_Detail!$AD$2:$AD$6492,"Linn") -> 5861749 | D10: =SUMIFS(Source_Detail!$AB$2:$AB$6492,Source_Detail!$B$2:$B$6492,$A10,Source_Detail!$AD$2:$AD$6492,"Linn") -> 1753926 | E10: =SUMIFS(Source_Detail!$O$2:$O$6492,Source_Detail!$B$2:$B$6492,$A10,Source_Detail!$AD$2:$AD$6492,"Linn") -> 694 | F10: =SUMIFS(Source_Detail!$P$2:$P$6492,Source_Detail!$B$2:$B$6492,$A10,Source_Detail!$AD$2:$AD$6492,"Linn") -> 115 | G10: =SUMIFS(Source_Detail!$Q$2:$Q$6492,Source_Detail!$B$2:$B$6492,$A10,Source_Detail!$AD$2:$AD$6492,"Linn") -> 1130 | H10: =SUMIFS(Source_Detail!$R$2:$R$6492,Source_Detail!$B$2:$B$6492,$A10,Source_Detail!$AD$2:$AD$6492,"Linn") -> 154 | I10: =SUMIFS(Source_Detail!$T$2:$T$6492,Source_Detail!$B$2:$B$6492,$A10,Source_Detail!$AD$2:$AD$6492,"Linn") -> 132168 | J10: =IFERROR(D10/C10,"N/M") -> 0.29921547 | K10: =IFERROR(C10/B10,"N/M") -> 0.058447477 | L10: =IFERROR(F10/E10,"N/M") -> 0.16570605 | M10: =IFERROR(D10/F10,"N/M") -> 15251.53 | O10: =SUMIFS(Source_Detail!$V$2:$V$6492,Source_Detail!$B$2:$B$6492,$A10,Source_Detail!$AD$2:$AD$6492,"Iowa ex-Linn") -> 8585818478 | P10: =SUMIFS(Source_Detail!$W$2:$W$6492,Source_Detail!$B$2:$B$6492,$A10,Source_Detail!$AD$2:$AD$6492,"Iowa ex-Linn") -> 598009859 | Q10: =SUMIFS(Source_Detail!$AB$2:$AB$6492,Source_Detail!$B$2:$B$6492,$A10,Source_Detail!$AD$2:$AD$6492,"Iowa ex-Linn") -> 74940125 | R10: =SUMIFS(Source_Detail!$O$2:$O$6492,Source_Detail!$B$2:$B$6492,$A10,Source_Detail!$AD$2:$AD$6492,"Iowa ex-Linn") -> 55667 | S10: =SUMIFS(Source_Detail!$P$2:$P$6492,Source_Detail!$B$2:$B$6492,$A10,Source_Detail!$AD$2:$AD$6492,"Iowa ex-Linn") -> 4746 | T10: =SUMIFS(Source_Detail!$Q$2:$Q$6492,Source_Detail!$B$2:$B$6492,$A10,Source_Detail!$AD$2:$AD$6492,"Iowa ex-Linn") -> 91229 | U10: =SUMIFS(Source_Detail!$R$2:$R$6492,Source_Detail!$B$2:$B$6492,$A10,Source_Detail!$AD$2:$AD$6492,"Iowa ex-Linn") -> 6393 | V10: =SUMIFS(Source_Detail!$T$2:$T$6492,Source_Detail!$B$2:$B$6492,$A10,Source_Detail!$AD$2:$AD$6492,"Iowa ex-Linn") -> 11553936 | W10: =IFERROR(Q10/P10,"N/M") -> 0.12531587 | X10: =IFERROR(P10/O10,"N/M") -> 0.069650885 | Y10: =IFERROR(S10/R10,"N/M") -> 0.085256975 | Z10: =IFERROR(Q10/S10,"N/M") -> 15790.165
A11: 2022 | B11: =SUMIFS(Source_Detail!$V$2:$V$6492,Source_Detail!$B$2:$B$6492,$A11,Source_Detail!$AD$2:$AD$6492,"Linn") -> 127791070 | C11: =SUMIFS(Source_Detail!$W$2:$W$6492,Source_Detail!$B$2:$B$6492,$A11,Source_Detail!$AD$2:$AD$6492,"Linn") -> 7545082 | D11: =SUMIFS(Source_Detail!$AB$2:$AB$6492,Source_Detail!$B$2:$B$6492,$A11,Source_Detail!$AD$2:$AD$6492,"Linn") -> 193749 | E11: =SUMIFS(Source_Detail!$O$2:$O$6492,Source_Detail!$B$2:$B$6492,$A11,Source_Detail!$AD$2:$AD$6492,"Linn") -> 672 | F11: =SUMIFS(Source_Detail!$P$2:$P$6492,Source_Detail!$B$2:$B$6492,$A11,Source_Detail!$AD$2:$AD$6492,"Linn") -> 15 | G11: =SUMIFS(Source_Detail!$Q$2:$Q$6492,Source_Detail!$B$2:$B$6492,$A11,Source_Detail!$AD$2:$AD$6492,"Linn") -> 1132 | H11: =SUMIFS(Source_Detail!$R$2:$R$6492,Source_Detail!$B$2:$B$6492,$A11,Source_Detail!$AD$2:$AD$6492,"Linn") -> 15 | I11: =SUMIFS(Source_Detail!$T$2:$T$6492,Source_Detail!$B$2:$B$6492,$A11,Source_Detail!$AD$2:$AD$6492,"Linn") -> 130218 | J11: =IFERROR(D11/C11,"N/M") -> 0.025678846 | K11: =IFERROR(C11/B11,"N/M") -> 0.059042326 | L11: =IFERROR(F11/E11,"N/M") -> 0.022321429 | M11: =IFERROR(D11/F11,"N/M") -> 12916.6 | O11: =SUMIFS(Source_Detail!$V$2:$V$6492,Source_Detail!$B$2:$B$6492,$A11,Source_Detail!$AD$2:$AD$6492,"Iowa ex-Linn") -> 11249540667 | P11: =SUMIFS(Source_Detail!$W$2:$W$6492,Source_Detail!$B$2:$B$6492,$A11,Source_Detail!$AD$2:$AD$6492,"Iowa ex-Linn") -> 779469417 | Q11: =SUMIFS(Source_Detail!$AB$2:$AB$6492,Source_Detail!$B$2:$B$6492,$A11,Source_Detail!$AD$2:$AD$6492,"Iowa ex-Linn") -> 177689585 | R11: =SUMIFS(Source_Detail!$O$2:$O$6492,Source_Detail!$B$2:$B$6492,$A11,Source_Detail!$AD$2:$AD$6492,"Iowa ex-Linn") -> 55840 | S11: =SUMIFS(Source_Detail!$P$2:$P$6492,Source_Detail!$B$2:$B$6492,$A11,Source_Detail!$AD$2:$AD$6492,"Iowa ex-Linn") -> 6923 | T11: =SUMIFS(Source_Detail!$Q$2:$Q$6492,Source_Detail!$B$2:$B$6492,$A11,Source_Detail!$AD$2:$AD$6492,"Iowa ex-Linn") -> 90107 | U11: =SUMIFS(Source_Detail!$R$2:$R$6492,Source_Detail!$B$2:$B$6492,$A11,Source_Detail!$AD$2:$AD$6492,"Iowa ex-Linn") -> 10036 | V11: =SUMIFS(Source_Detail!$T$2:$T$6492,Source_Detail!$B$2:$B$6492,$A11,Source_Detail!$AD$2:$AD$6492,"Iowa ex-Linn") -> 11614205 | W11: =IFERROR(Q11/P11,"N/M") -> 0.22796223 | X11: =IFERROR(P11/O11,"N/M") -> 0.069288999 | Y11: =IFERROR(S11/R11,"N/M") -> 0.12397923 | Z11: =IFERROR(Q11/S11,"N/M") -> 25666.559
A12: 2023 | B12: =SUMIFS(Source_Detail!$V$2:$V$6492,Source_Detail!$B$2:$B$6492,$A12,Source_Detail!$AD$2:$AD$6492,"Linn") -> 138661129 | C12: =SUMIFS(Source_Detail!$W$2:$W$6492,Source_Detail!$B$2:$B$6492,$A12,Source_Detail!$AD$2:$AD$6492,"Linn") -> 6480635 | D12: =SUMIFS(Source_Detail!$AB$2:$AB$6492,Source_Detail!$B$2:$B$6492,$A12,Source_Detail!$AD$2:$AD$6492,"Linn") -> 26854510 | E12: =SUMIFS(Source_Detail!$O$2:$O$6492,Source_Detail!$B$2:$B$6492,$A12,Source_Detail!$AD$2:$AD$6492,"Linn") -> 697 | F12: =SUMIFS(Source_Detail!$P$2:$P$6492,Source_Detail!$B$2:$B$6492,$A12,Source_Detail!$AD$2:$AD$6492,"Linn") -> 612 | G12: =SUMIFS(Source_Detail!$Q$2:$Q$6492,Source_Detail!$B$2:$B$6492,$A12,Source_Detail!$AD$2:$AD$6492,"Linn") -> 1105 | H12: =SUMIFS(Source_Detail!$R$2:$R$6492,Source_Detail!$B$2:$B$6492,$A12,Source_Detail!$AD$2:$AD$6492,"Linn") -> 950 | I12: =SUMIFS(Source_Detail!$T$2:$T$6492,Source_Detail!$B$2:$B$6492,$A12,Source_Detail!$AD$2:$AD$6492,"Linn") -> 136455 | J12: =IFERROR(D12/C12,"N/M") -> 4.1438084 | K12: =IFERROR(C12/B12,"N/M") -> 0.046737215 | L12: =IFERROR(F12/E12,"N/M") -> 0.87804878 | M12: =IFERROR(D12/F12,"N/M") -> 43879.918 | O12: =SUMIFS(Source_Detail!$V$2:$V$6492,Source_Detail!$B$2:$B$6492,$A12,Source_Detail!$AD$2:$AD$6492,"Iowa ex-Linn") -> 11681258319 | P12: =SUMIFS(Source_Detail!$W$2:$W$6492,Source_Detail!$B$2:$B$6492,$A12,Source_Detail!$AD$2:$AD$6492,"Iowa ex-Linn") -> 651049952 | Q12: =SUMIFS(Source_Detail!$AB$2:$AB$6492,Source_Detail!$B$2:$B$6492,$A12,Source_Detail!$AD$2:$AD$6492,"Iowa ex-Linn") -> 672664371 | R12: =SUMIFS(Source_Detail!$O$2:$O$6492,Source_Detail!$B$2:$B$6492,$A12,Source_Detail!$AD$2:$AD$6492,"Iowa ex-Linn") -> 55835 | S12: =SUMIFS(Source_Detail!$P$2:$P$6492,Source_Detail!$B$2:$B$6492,$A12,Source_Detail!$AD$2:$AD$6492,"Iowa ex-Linn") -> 23382 | T12: =SUMIFS(Source_Detail!$Q$2:$Q$6492,Source_Detail!$B$2:$B$6492,$A12,Source_Detail!$AD$2:$AD$6492,"Iowa ex-Linn") -> 89910 | U12: =SUMIFS(Source_Detail!$R$2:$R$6492,Source_Detail!$B$2:$B$6492,$A12,Source_Detail!$AD$2:$AD$6492,"Iowa ex-Linn") -> 34455 | V12: =SUMIFS(Source_Detail!$T$2:$T$6492,Source_Detail!$B$2:$B$6492,$A12,Source_Detail!$AD$2:$AD$6492,"Iowa ex-Linn") -> 11733352 | W12: =IFERROR(Q12/P12,"N/M") -> 1.0331993 | X12: =IFERROR(P12/O12,"N/M") -> 0.055734574 | Y12: =IFERROR(S12/R12,"N/M") -> 0.41876959 | Z12: =IFERROR(Q12/S12,"N/M") -> 28768.47
A13: 2024 | B13: =SUMIFS(Source_Detail!$V$2:$V$6492,Source_Detail!$B$2:$B$6492,$A13,Source_Detail!$AD$2:$AD$6492,"Linn") -> 106454332 | C13: =SUMIFS(Source_Detail!$W$2:$W$6492,Source_Detail!$B$2:$B$6492,$A13,Source_Detail!$AD$2:$AD$6492,"Linn") -> 6008122 | D13: =SUMIFS(Source_Detail!$AB$2:$AB$6492,Source_Detail!$B$2:$B$6492,$A13,Source_Detail!$AD$2:$AD$6492,"Linn") -> 363811 | E13: =SUMIFS(Source_Detail!$O$2:$O$6492,Source_Detail!$B$2:$B$6492,$A13,Source_Detail!$AD$2:$AD$6492,"Linn") -> 689 | F13: =SUMIFS(Source_Detail!$P$2:$P$6492,Source_Detail!$B$2:$B$6492,$A13,Source_Detail!$AD$2:$AD$6492,"Linn") -> 51 | G13: =SUMIFS(Source_Detail!$Q$2:$Q$6492,Source_Detail!$B$2:$B$6492,$A13,Source_Detail!$AD$2:$AD$6492,"Linn") -> 1124 | H13: =SUMIFS(Source_Detail!$R$2:$R$6492,Source_Detail!$B$2:$B$6492,$A13,Source_Detail!$AD$2:$AD$6492,"Linn") -> 63 | I13: =SUMIFS(Source_Detail!$T$2:$T$6492,Source_Detail!$B$2:$B$6492,$A13,Source_Detail!$AD$2:$AD$6492,"Linn") -> 131975 | J13: =IFERROR(D13/C13,"N/M") -> 0.060553198 | K13: =IFERROR(C13/B13,"N/M") -> 0.056438492 | L13: =IFERROR(F13/E13,"N/M") -> 0.074020319 | M13: =IFERROR(D13/F13,"N/M") -> 7133.549 | O13: =SUMIFS(Source_Detail!$V$2:$V$6492,Source_Detail!$B$2:$B$6492,$A13,Source_Detail!$AD$2:$AD$6492,"Iowa ex-Linn") -> 9343921778 | P13: =SUMIFS(Source_Detail!$W$2:$W$6492,Source_Detail!$B$2:$B$6492,$A13,Source_Detail!$AD$2:$AD$6492,"Iowa ex-Linn") -> 570477901 | Q13: =SUMIFS(Source_Detail!$AB$2:$AB$6492,Source_Detail!$B$2:$B$6492,$A13,Source_Detail!$AD$2:$AD$6492,"Iowa ex-Linn") -> 230899951 | R13: =SUMIFS(Source_Detail!$O$2:$O$6492,Source_Detail!$B$2:$B$6492,$A13,Source_Detail!$AD$2:$AD$6492,"Iowa ex-Linn") -> 55754 | S13: =SUMIFS(Source_Detail!$P$2:$P$6492,Source_Detail!$B$2:$B$6492,$A13,Source_Detail!$AD$2:$AD$6492,"Iowa ex-Linn") -> 13453 | T13: =SUMIFS(Source_Detail!$Q$2:$Q$6492,Source_Detail!$B$2:$B$6492,$A13,Source_Detail!$AD$2:$AD$6492,"Iowa ex-Linn") -> 89832 | U13: =SUMIFS(Source_Detail!$R$2:$R$6492,Source_Detail!$B$2:$B$6492,$A13,Source_Detail!$AD$2:$AD$6492,"Iowa ex-Linn") -> 19557 | V13: =SUMIFS(Source_Detail!$T$2:$T$6492,Source_Detail!$B$2:$B$6492,$A13,Source_Detail!$AD$2:$AD$6492,"Iowa ex-Linn") -> 11737804 | W13: =IFERROR(Q13/P13,"N/M") -> 0.40474828 | X13: =IFERROR(P13/O13,"N/M") -> 0.061053369 | Y13: =IFERROR(S13/R13,"N/M") -> 0.2412921 | Z13: =IFERROR(Q13/S13,"N/M") -> 17163.454
A16: Loss-ratio selection horizons
A17: Horizon | B17: Start | C17: End | D17: Weight | E17: Linn Premium | F17: Linn Indemnity | G17: Linn LR | H17: Complement Premium | I17: Complement Indemnity | J17: Complement LR
A18: 3-year | B18: 2022 | C18: 2024 | D18: 0.2 | E18: =SUMIFS($C$4:$C$13,$A$4:$A$13,">="&B18,$A$4:$A$13,"<="&C18) -> 20033839 | F18: =SUMIFS($D$4:$D$13,$A$4:$A$13,">="&B18,$A$4:$A$13,"<="&C18) -> 27412070 | G18: =IFERROR(F18/E18,"N/M") -> 1.3682884 | H18: =SUMIFS($P$4:$P$13,$A$4:$A$13,">="&B18,$A$4:$A$13,"<="&C18) -> 2000997270 | I18: =SUMIFS($Q$4:$Q$13,$A$4:$A$13,">="&B18,$A$4:$A$13,"<="&C18) -> 1081253907 | J18: =IFERROR(I18/H18,"N/M") -> 0.54035751
A19: 5-year | B19: 2020 | C19: 2024 | D19: 0.3 | E19: =SUMIFS($C$4:$C$13,$A$4:$A$13,">="&B19,$A$4:$A$13,"<="&C19) -> 29334124 | F19: =SUMIFS($D$4:$D$13,$A$4:$A$13,">="&B19,$A$4:$A$13,"<="&C19) -> 46126238 | G19: =IFERROR(F19/E19,"N/M") -> 1.572443 | H19: =SUMIFS($P$4:$P$13,$A$4:$A$13,">="&B19,$A$4:$A$13,"<="&C19) -> 2976442580 | I19: =SUMIFS($Q$4:$Q$13,$A$4:$A$13,">="&B19,$A$4:$A$13,"<="&C19) -> 1644829709 | J19: =IFERROR(I19/H19,"N/M") -> 0.55261597
A20: 10-year | B20: 2015 | C20: 2024 | D20: 0.5 | E20: =SUMIFS($C$4:$C$13,$A$4:$A$13,">="&B20,$A$4:$A$13,"<="&C20) -> 48899058 | F20: =SUMIFS($D$4:$D$13,$A$4:$A$13,">="&B20,$A$4:$A$13,"<="&C20) -> 47945371 | G20: =IFERROR(F20/E20,"N/M") -> 0.98049682 | H20: =SUMIFS($P$4:$P$13,$A$4:$A$13,">="&B20,$A$4:$A$13,"<="&C20) -> 5051186245 | I20: =SUMIFS($Q$4:$Q$13,$A$4:$A$13,">="&B20,$A$4:$A$13,"<="&C20) -> 2237759108 | J20: =IFERROR(I20/H20,"N/M") -> 0.44301655
A21: Weighted horizon selection | B21: 20% × 3-year + 30% × 5-year + 50% × 10-year | G21: =SUMPRODUCT(D18:D20,G18:G20) -> 1.235639 | H21: Iowa ex-Linn selection | J21: =SUMPRODUCT(D18:D20,J18:J20) -> 0.49536457

Sheet Coverage_Experience
A1: Coverage-level experience | 2015–2024
A2: Linn County compared with the non-overlapping Iowa complement · thin levels remain visible as not meaningful
A3: Coverage Level | B3: Linn Liability | C3: Linn Base Premium | D3: Linn Indemnity | E3: Linn Policies Earning | F3: Linn Policies Indemnified | G3: Linn Units Earning | H3: Linn Units Indemnified | I3: Linn Acres | J3: Linn Loss Ratio | K3: Linn Rate on Liability | L3: Linn Policy Claim Frequency | M3: Linn Severity | O3: Iowa ex-Linn Liability | P3: Iowa ex-Linn Base Premium | Q3: Iowa ex-Linn Indemnity | R3: Iowa ex-Linn Policies Earning | S3: Iowa ex-Linn Policies Indemnified | T3: Iowa ex-Linn Units Earning | U3: Iowa ex-Linn Units Indemnified | V3: Iowa ex-Linn Acres | W3: Iowa ex-Linn Loss Ratio | X3: Iowa ex-Linn Rate on Liability | Y3: Iowa ex-Linn Policy Claim Frequency | Z3: Iowa ex-Linn Severity
A4: 0.5 | B4: =SUMIFS(Source_Detail!$V$2:$V$6492,Source_Detail!$M$2:$M$6492,$A4,Source_Detail!$AD$2:$AD$6492,"Linn") -> 42853 | C4: =SUMIFS(Source_Detail!$W$2:$W$6492,Source_Detail!$M$2:$M$6492,$A4,Source_Detail!$AD$2:$AD$6492,"Linn") -> 214 | D4: =SUMIFS(Source_Detail!$AB$2:$AB$6492,Source_Detail!$M$2:$M$6492,$A4,Source_Detail!$AD$2:$AD$6492,"Linn") -> 0 | E4: =SUMIFS(Source_Detail!$O$2:$O$6492,Source_Detail!$M$2:$M$6492,$A4,Source_Detail!$AD$2:$AD$6492,"Linn") -> 2 | F4: =SUMIFS(Source_Detail!$P$2:$P$6492,Source_Detail!$M$2:$M$6492,$A4,Source_Detail!$AD$2:$AD$6492,"Linn") -> 0 | G4: =SUMIFS(Source_Detail!$Q$2:$Q$6492,Source_Detail!$M$2:$M$6492,$A4,Source_Detail!$AD$2:$AD$6492,"Linn") -> 2 | H4: =SUMIFS(Source_Detail!$R$2:$R$6492,Source_Detail!$M$2:$M$6492,$A4,Source_Detail!$AD$2:$AD$6492,"Linn") -> 0 | I4: =SUMIFS(Source_Detail!$T$2:$T$6492,Source_Detail!$M$2:$M$6492,$A4,Source_Detail!$AD$2:$AD$6492,"Linn") -> 122 | J4: =IFERROR(D4/C4,"N/M") -> 0 | K4: =IFERROR(C4/B4,"N/M") -> 0.0049938161 | L4: =IFERROR(F4/E4,"N/M") -> 0 | M4: =IFERROR(D4/F4,"N/M") -> N/M | O4: =SUMIFS(Source_Detail!$V$2:$V$6492,Source_Detail!$M$2:$M$6492,$A4,Source_Detail!$AD$2:$AD$6492,"Iowa ex-Linn") -> 72984044 | P4: =SUMIFS(Source_Detail!$W$2:$W$6492,Source_Detail!$M$2:$M$6492,$A4,Source_Detail!$AD$2:$AD$6492,"Iowa ex-Linn") -> 1017419 | Q4: =SUMIFS(Source_Detail!$AB$2:$AB$6492,Source_Detail!$M$2:$M$6492,$A4,Source_Detail!$AD$2:$AD$6492,"Iowa ex-Linn") -> 255656 | R4: =SUMIFS(Source_Detail!$O$2:$O$6492,Source_Detail!$M$2:$M$6492,$A4,Source_Detail!$AD$2:$AD$6492,"Iowa ex-Linn") -> 841 | S4: =SUMIFS(Source_Detail!$P$2:$P$6492,Source_Detail!$M$2:$M$6492,$A4,Source_Detail!$AD$2:$AD$6492,"Iowa ex-Linn") -> 32 | T4: =SUMIFS(Source_Detail!$Q$2:$Q$6492,Source_Detail!$M$2:$M$6492,$A4,Source_Detail!$AD$2:$AD$6492,"Iowa ex-Linn") -> 1154 | U4: =SUMIFS(Source_Detail!$R$2:$R$6492,Source_Detail!$M$2:$M$6492,$A4,Source_Detail!$AD$2:$AD$6492,"Iowa ex-Linn") -> 47 | V4: =SUMIFS(Source_Detail!$T$2:$T$6492,Source_Detail!$M$2:$M$6492,$A4,Source_Detail!$AD$2:$AD$6492,"Iowa ex-Linn") -> 166547 | W4: =IFERROR(Q4/P4,"N/M") -> 0.25127897 | X4: =IFERROR(P4/O4,"N/M") -> 0.013940294 | Y4: =IFERROR(S4/R4,"N/M") -> 0.038049941 | Z4: =IFERROR(Q4/S4,"N/M") -> 7989.25
A5: 0.55 | B5: =SUMIFS(Source_Detail!$V$2:$V$6492,Source_Detail!$M$2:$M$6492,$A5,Source_Detail!$AD$2:$AD$6492,"Linn") -> 594070 | C5: =SUMIFS(Source_Detail!$W$2:$W$6492,Source_Detail!$M$2:$M$6492,$A5,Source_Detail!$AD$2:$AD$6492,"Linn") -> 3711 | D5: =SUMIFS(Source_Detail!$AB$2:$AB$6492,Source_Detail!$M$2:$M$6492,$A5,Source_Detail!$AD$2:$AD$6492,"Linn") -> 0 | E5: =SUMIFS(Source_Detail!$O$2:$O$6492,Source_Detail!$M$2:$M$6492,$A5,Source_Detail!$AD$2:$AD$6492,"Linn") -> 2 | F5: =SUMIFS(Source_Detail!$P$2:$P$6492,Source_Detail!$M$2:$M$6492,$A5,Source_Detail!$AD$2:$AD$6492,"Linn") -> 0 | G5: =SUMIFS(Source_Detail!$Q$2:$Q$6492,Source_Detail!$M$2:$M$6492,$A5,Source_Detail!$AD$2:$AD$6492,"Linn") -> 12 | H5: =SUMIFS(Source_Detail!$R$2:$R$6492,Source_Detail!$M$2:$M$6492,$A5,Source_Detail!$AD$2:$AD$6492,"Linn") -> 0 | I5: =SUMIFS(Source_Detail!$T$2:$T$6492,Source_Detail!$M$2:$M$6492,$A5,Source_Detail!$AD$2:$AD$6492,"Linn") -> 1187 | J5: =IFERROR(D5/C5,"N/M") -> 0 | K5: =IFERROR(C5/B5,"N/M") -> 0.0062467386 | L5: =IFERROR(F5/E5,"N/M") -> 0 | M5: =IFERROR(D5/F5,"N/M") -> N/M | O5: =SUMIFS(Source_Detail!$V$2:$V$6492,Source_Detail!$M$2:$M$6492,$A5,Source_Detail!$AD$2:$AD$6492,"Iowa ex-Linn") -> 33300743 | P5: =SUMIFS(Source_Detail!$W$2:$W$6492,Source_Detail!$M$2:$M$6492,$A5,Source_Detail!$AD$2:$AD$6492,"Iowa ex-Linn") -> 646220 | Q5: =SUMIFS(Source_Detail!$AB$2:$AB$6492,Source_Detail!$M$2:$M$6492,$A5,Source_Detail!$AD$2:$AD$6492,"Iowa ex-Linn") -> 264298 | R5: =SUMIFS(Source_Detail!$O$2:$O$6492,Source_Detail!$M$2:$M$6492,$A5,Source_Detail!$AD$2:$AD$6492,"Iowa ex-Linn") -> 236 | S5: =SUMIFS(Source_Detail!$P$2:$P$6492,Source_Detail!$M$2:$M$6492,$A5,Source_Detail!$AD$2:$AD$6492,"Iowa ex-Linn") -> 22 | T5: =SUMIFS(Source_Detail!$Q$2:$Q$6492,Source_Detail!$M$2:$M$6492,$A5,Source_Detail!$AD$2:$AD$6492,"Iowa ex-Linn") -> 338 | U5: =SUMIFS(Source_Detail!$R$2:$R$6492,Source_Detail!$M$2:$M$6492,$A5,Source_Detail!$AD$2:$AD$6492,"Iowa ex-Linn") -> 27 | V5: =SUMIFS(Source_Detail!$T$2:$T$6492,Source_Detail!$M$2:$M$6492,$A5,Source_Detail!$AD$2:$AD$6492,"Iowa ex-Linn") -> 68803 | W5: =IFERROR(Q5/P5,"N/M") -> 0.40899075 | X5: =IFERROR(P5/O5,"N/M") -> 0.019405573 | Y5: =IFERROR(S5/R5,"N/M") -> 0.093220339 | Z5: =IFERROR(Q5/S5,"N/M") -> 12013.545
A6: 0.6 | B6: =SUMIFS(Source_Detail!$V$2:$V$6492,Source_Detail!$M$2:$M$6492,$A6,Source_Detail!$AD$2:$AD$6492,"Linn") -> 0 | C6: =SUMIFS(Source_Detail!$W$2:$W$6492,Source_Detail!$M$2:$M$6492,$A6,Source_Detail!$AD$2:$AD$6492,"Linn") -> 0 | D6: =SUMIFS(Source_Detail!$AB$2:$AB$6492,Source_Detail!$M$2:$M$6492,$A6,Source_Detail!$AD$2:$AD$6492,"Linn") -> 0 | E6: =SUMIFS(Source_Detail!$O$2:$O$6492,Source_Detail!$M$2:$M$6492,$A6,Source_Detail!$AD$2:$AD$6492,"Linn") -> 0 | F6: =SUMIFS(Source_Detail!$P$2:$P$6492,Source_Detail!$M$2:$M$6492,$A6,Source_Detail!$AD$2:$AD$6492,"Linn") -> 0 | G6: =SUMIFS(Source_Detail!$Q$2:$Q$6492,Source_Detail!$M$2:$M$6492,$A6,Source_Detail!$AD$2:$AD$6492,"Linn") -> 0 | H6: =SUMIFS(Source_Detail!$R$2:$R$6492,Source_Detail!$M$2:$M$6492,$A6,Source_Detail!$AD$2:$AD$6492,"Linn") -> 0 | I6: =SUMIFS(Source_Detail!$T$2:$T$6492,Source_Detail!$M$2:$M$6492,$A6,Source_Detail!$AD$2:$AD$6492,"Linn") -> 0 | J6: =IFERROR(D6/C6,"N/M") -> N/M | K6: =IFERROR(C6/B6,"N/M") -> N/M | L6: =IFERROR(F6/E6,"N/M") -> N/M | M6: =IFERROR(D6/F6,"N/M") -> N/M | O6: =SUMIFS(Source_Detail!$V$2:$V$6492,Source_Detail!$M$2:$M$6492,$A6,Source_Detail!$AD$2:$AD$6492,"Iowa ex-Linn") -> 103677487 | P6: =SUMIFS(Source_Detail!$W$2:$W$6492,Source_Detail!$M$2:$M$6492,$A6,Source_Detail!$AD$2:$AD$6492,"Iowa ex-Linn") -> 2211923 | Q6: =SUMIFS(Source_Detail!$AB$2:$AB$6492,Source_Detail!$M$2:$M$6492,$A6,Source_Detail!$AD$2:$AD$6492,"Iowa ex-Linn") -> 357973 | R6: =SUMIFS(Source_Detail!$O$2:$O$6492,Source_Detail!$M$2:$M$6492,$A6,Source_Detail!$AD$2:$AD$6492,"Iowa ex-Linn") -> 1106 | S6: =SUMIFS(Source_Detail!$P$2:$P$6492,Source_Detail!$M$2:$M$6492,$A6,Source_Detail!$AD$2:$AD$6492,"Iowa ex-Linn") -> 56 | T6: =SUMIFS(Source_Detail!$Q$2:$Q$6492,Source_Detail!$M$2:$M$6492,$A6,Source_Detail!$AD$2:$AD$6492,"Iowa ex-Linn") -> 1652 | U6: =SUMIFS(Source_Detail!$R$2:$R$6492,Source_Detail!$M$2:$M$6492,$A6,Source_Detail!$AD$2:$AD$6492,"Iowa ex-Linn") -> 78 | V6: =SUMIFS(Source_Detail!$T$2:$T$6492,Source_Detail!$M$2:$M$6492,$A6,Source_Detail!$AD$2:$AD$6492,"Iowa ex-Linn") -> 194586 | W6: =IFERROR(Q6/P6,"N/M") -> 0.16183791 | X6: =IFERROR(P6/O6,"N/M") -> 0.021334651 | Y6: =IFERROR(S6/R6,"N/M") -> 0.050632911 | Z6: =IFERROR(Q6/S6,"N/M") -> 6392.375
A7: 0.65 | B7: =SUMIFS(Source_Detail!$V$2:$V$6492,Source_Detail!$M$2:$M$6492,$A7,Source_Detail!$AD$2:$AD$6492,"Linn") -> 1343429 | C7: =SUMIFS(Source_Detail!$W$2:$W$6492,Source_Detail!$M$2:$M$6492,$A7,Source_Detail!$AD$2:$AD$6492,"Linn") -> 29480 | D7: =SUMIFS(Source_Detail!$AB$2:$AB$6492,Source_Detail!$M$2:$M$6492,$A7,Source_Detail!$AD$2:$AD$6492,"Linn") -> 48540 | E7: =SUMIFS(Source_Detail!$O$2:$O$6492,Source_Detail!$M$2:$M$6492,$A7,Source_Detail!$AD$2:$AD$6492,"Linn") -> 55 | F7: =SUMIFS(Source_Detail!$P$2:$P$6492,Source_Detail!$M$2:$M$6492,$A7,Source_Detail!$AD$2:$AD$6492,"Linn") -> 6 | G7: =SUMIFS(Source_Detail!$Q$2:$Q$6492,Source_Detail!$M$2:$M$6492,$A7,Source_Detail!$AD$2:$AD$6492,"Linn") -> 58 | H7: =SUMIFS(Source_Detail!$R$2:$R$6492,Source_Detail!$M$2:$M$6492,$A7,Source_Detail!$AD$2:$AD$6492,"Linn") -> 6 | I7: =SUMIFS(Source_Detail!$T$2:$T$6492,Source_Detail!$M$2:$M$6492,$A7,Source_Detail!$AD$2:$AD$6492,"Linn") -> 2544 | J7: =IFERROR(D7/C7,"N/M") -> 1.64654 | K7: =IFERROR(C7/B7,"N/M") -> 0.021943847 | L7: =IFERROR(F7/E7,"N/M") -> 0.10909091 | M7: =IFERROR(D7/F7,"N/M") -> 8090 | O7: =SUMIFS(Source_Detail!$V$2:$V$6492,Source_Detail!$M$2:$M$6492,$A7,Source_Detail!$AD$2:$AD$6492,"Iowa ex-Linn") -> 343609328 | P7: =SUMIFS(Source_Detail!$W$2:$W$6492,Source_Detail!$M$2:$M$6492,$A7,Source_Detail!$AD$2:$AD$6492,"Iowa ex-Linn") -> 9718217 | Q7: =SUMIFS(Source_Detail!$AB$2:$AB$6492,Source_Detail!$M$2:$M$6492,$A7,Source_Detail!$AD$2:$AD$6492,"Iowa ex-Linn") -> 2951555 | R7: =SUMIFS(Source_Detail!$O$2:$O$6492,Source_Detail!$M$2:$M$6492,$A7,Source_Detail!$AD$2:$AD$6492,"Iowa ex-Linn") -> 5238 | S7: =SUMIFS(Source_Detail!$P$2:$P$6492,Source_Detail!$M$2:$M$6492,$A7,Source_Detail!$AD$2:$AD$6492,"Iowa ex-Linn") -> 328 | T7: =SUMIFS(Source_Detail!$Q$2:$Q$6492,Source_Detail!$M$2:$M$6492,$A7,Source_Detail!$AD$2:$AD$6492,"Iowa ex-Linn") -> 7549 | U7: =SUMIFS(Source_Detail!$R$2:$R$6492,Source_Detail!$M$2:$M$6492,$A7,Source_Detail!$AD$2:$AD$6492,"Iowa ex-Linn") -> 408 | V7: =SUMIFS(Source_Detail!$T$2:$T$6492,Source_Detail!$M$2:$M$6492,$A7,Source_Detail!$AD$2:$AD$6492,"Iowa ex-Linn") -> 617443 | W7: =IFERROR(Q7/P7,"N/M") -> 0.30371363 | X7: =IFERROR(P7/O7,"N/M") -> 0.028282751 | Y7: =IFERROR(S7/R7,"N/M") -> 0.06261932 | Z7: =IFERROR(Q7/S7,"N/M") -> 8998.6433
A8: 0.7 | B8: =SUMIFS(Source_Detail!$V$2:$V$6492,Source_Detail!$M$2:$M$6492,$A8,Source_Detail!$AD$2:$AD$6492,"Linn") -> 5941966 | C8: =SUMIFS(Source_Detail!$W$2:$W$6492,Source_Detail!$M$2:$M$6492,$A8,Source_Detail!$AD$2:$AD$6492,"Linn") -> 132321 | D8: =SUMIFS(Source_Detail!$AB$2:$AB$6492,Source_Detail!$M$2:$M$6492,$A8,Source_Detail!$AD$2:$AD$6492,"Linn") -> 92025 | E8: =SUMIFS(Source_Detail!$O$2:$O$6492,Source_Detail!$M$2:$M$6492,$A8,Source_Detail!$AD$2:$AD$6492,"Linn") -> 143 | F8: =SUMIFS(Source_Detail!$P$2:$P$6492,Source_Detail!$M$2:$M$6492,$A8,Source_Detail!$AD$2:$AD$6492,"Linn") -> 16 | G8: =SUMIFS(Source_Detail!$Q$2:$Q$6492,Source_Detail!$M$2:$M$6492,$A8,Source_Detail!$AD$2:$AD$6492,"Linn") -> 176 | H8: =SUMIFS(Source_Detail!$R$2:$R$6492,Source_Detail!$M$2:$M$6492,$A8,Source_Detail!$AD$2:$AD$6492,"Linn") -> 18 | I8: =SUMIFS(Source_Detail!$T$2:$T$6492,Source_Detail!$M$2:$M$6492,$A8,Source_Detail!$AD$2:$AD$6492,"Linn") -> 10590 | J8: =IFERROR(D8/C8,"N/M") -> 0.69546784 | K8: =IFERROR(C8/B8,"N/M") -> 0.022268892 | L8: =IFERROR(F8/E8,"N/M") -> 0.11188811 | M8: =IFERROR(D8/F8,"N/M") -> 5751.5625 | O8: =SUMIFS(Source_Detail!$V$2:$V$6492,Source_Detail!$M$2:$M$6492,$A8,Source_Detail!$AD$2:$AD$6492,"Iowa ex-Linn") -> 1834101992 | P8: =SUMIFS(Source_Detail!$W$2:$W$6492,Source_Detail!$M$2:$M$6492,$A8,Source_Detail!$AD$2:$AD$6492,"Iowa ex-Linn") -> 77552121 | Q8: =SUMIFS(Source_Detail!$AB$2:$AB$6492,Source_Detail!$M$2:$M$6492,$A8,Source_Detail!$AD$2:$AD$6492,"Iowa ex-Linn") -> 24130848 | R8: =SUMIFS(Source_Detail!$O$2:$O$6492,Source_Detail!$M$2:$M$6492,$A8,Source_Detail!$AD$2:$AD$6492,"Iowa ex-Linn") -> 23380 | S8: =SUMIFS(Source_Detail!$P$2:$P$6492,Source_Detail!$M$2:$M$6492,$A8,Source_Detail!$AD$2:$AD$6492,"Iowa ex-Linn") -> 2320 | T8: =SUMIFS(Source_Detail!$Q$2:$Q$6492,Source_Detail!$M$2:$M$6492,$A8,Source_Detail!$AD$2:$AD$6492,"Iowa ex-Linn") -> 35567 | U8: =SUMIFS(Source_Detail!$R$2:$R$6492,Source_Detail!$M$2:$M$6492,$A8,Source_Detail!$AD$2:$AD$6492,"Iowa ex-Linn") -> 3123 | V8: =SUMIFS(Source_Detail!$T$2:$T$6492,Source_Detail!$M$2:$M$6492,$A8,Source_Detail!$AD$2:$AD$6492,"Iowa ex-Linn") -> 3036280 | W8: =IFERROR(Q8/P8,"N/M") -> 0.31115652 | X8: =IFERROR(P8/O8,"N/M") -> 0.042283429 | Y8: =IFERROR(S8/R8,"N/M") -> 0.099230111 | Z8: =IFERROR(Q8/S8,"N/M") -> 10401.228
A9: 0.75 | B9: =SUMIFS(Source_Detail!$V$2:$V$6492,Source_Detail!$M$2:$M$6492,$A9,Source_Detail!$AD$2:$AD$6492,"Linn") -> 71132867 | C9: =SUMIFS(Source_Detail!$W$2:$W$6492,Source_Detail!$M$2:$M$6492,$A9,Source_Detail!$AD$2:$AD$6492,"Linn") -> 2370244 | D9: =SUMIFS(Source_Detail!$AB$2:$AB$6492,Source_Detail!$M$2:$M$6492,$A9,Source_Detail!$AD$2:$AD$6492,"Linn") -> 2795599 | E9: =SUMIFS(Source_Detail!$O$2:$O$6492,Source_Detail!$M$2:$M$6492,$A9,Source_Detail!$AD$2:$AD$6492,"Linn") -> 804 | F9: =SUMIFS(Source_Detail!$P$2:$P$6492,Source_Detail!$M$2:$M$6492,$A9,Source_Detail!$AD$2:$AD$6492,"Linn") -> 133 | G9: =SUMIFS(Source_Detail!$Q$2:$Q$6492,Source_Detail!$M$2:$M$6492,$A9,Source_Detail!$AD$2:$AD$6492,"Linn") -> 1278 | H9: =SUMIFS(Source_Detail!$R$2:$R$6492,Source_Detail!$M$2:$M$6492,$A9,Source_Detail!$AD$2:$AD$6492,"Linn") -> 206 | I9: =SUMIFS(Source_Detail!$T$2:$T$6492,Source_Detail!$M$2:$M$6492,$A9,Source_Detail!$AD$2:$AD$6492,"Linn") -> 104998 | J9: =IFERROR(D9/C9,"N/M") -> 1.1794562 | K9: =IFERROR(C9/B9,"N/M") -> 0.033321362 | L9: =IFERROR(F9/E9,"N/M") -> 0.16542289 | M9: =IFERROR(D9/F9,"N/M") -> 21019.541 | O9: =SUMIFS(Source_Detail!$V$2:$V$6492,Source_Detail!$M$2:$M$6492,$A9,Source_Detail!$AD$2:$AD$6492,"Iowa ex-Linn") -> 9853259040 | P9: =SUMIFS(Source_Detail!$W$2:$W$6492,Source_Detail!$M$2:$M$6492,$A9,Source_Detail!$AD$2:$AD$6492,"Iowa ex-Linn") -> 511099690 | Q9: =SUMIFS(Source_Detail!$AB$2:$AB$6492,Source_Detail!$M$2:$M$6492,$A9,Source_Detail!$AD$2:$AD$6492,"Iowa ex-Linn") -> 160179094 | R9: =SUMIFS(Source_Detail!$O$2:$O$6492,Source_Detail!$M$2:$M$6492,$A9,Source_Detail!$AD$2:$AD$6492,"Iowa ex-Linn") -> 91956 | S9: =SUMIFS(Source_Detail!$P$2:$P$6492,Source_Detail!$M$2:$M$6492,$A9,Source_Detail!$AD$2:$AD$6492,"Iowa ex-Linn") -> 11768 | T9: =SUMIFS(Source_Detail!$Q$2:$Q$6492,Source_Detail!$M$2:$M$6492,$A9,Source_Detail!$AD$2:$AD$6492,"Iowa ex-Linn") -> 141647 | U9: =SUMIFS(Source_Detail!$R$2:$R$6492,Source_Detail!$M$2:$M$6492,$A9,Source_Detail!$AD$2:$AD$6492,"Iowa ex-Linn") -> 16125 | V9: =SUMIFS(Source_Detail!$T$2:$T$6492,Source_Detail!$M$2:$M$6492,$A9,Source_Detail!$AD$2:$AD$6492,"Iowa ex-Linn") -> 15100781 | W9: =IFERROR(Q9/P9,"N/M") -> 0.31340088 | X9: =IFERROR(P9/O9,"N/M") -> 0.051871131 | Y9: =IFERROR(S9/R9,"N/M") -> 0.12797425 | Z9: =IFERROR(Q9/S9,"N/M") -> 13611.412
A10: 0.8 | B10: =SUMIFS(Source_Detail!$V$2:$V$6492,Source_Detail!$M$2:$M$6492,$A10,Source_Detail!$AD$2:$AD$6492,"Linn") -> 403051644 | C10: =SUMIFS(Source_Detail!$W$2:$W$6492,Source_Detail!$M$2:$M$6492,$A10,Source_Detail!$AD$2:$AD$6492,"Linn") -> 17931850 | D10: =SUMIFS(Source_Detail!$AB$2:$AB$6492,Source_Detail!$M$2:$M$6492,$A10,Source_Detail!$AD$2:$AD$6492,"Linn") -> 18849953 | E10: =SUMIFS(Source_Detail!$O$2:$O$6492,Source_Detail!$M$2:$M$6492,$A10,Source_Detail!$AD$2:$AD$6492,"Linn") -> 2921 | F10: =SUMIFS(Source_Detail!$P$2:$P$6492,Source_Detail!$M$2:$M$6492,$A10,Source_Detail!$AD$2:$AD$6492,"Linn") -> 605 | G10: =SUMIFS(Source_Detail!$Q$2:$Q$6492,Source_Detail!$M$2:$M$6492,$A10,Source_Detail!$AD$2:$AD$6492,"Linn") -> 4858 | H10: =SUMIFS(Source_Detail!$R$2:$R$6492,Source_Detail!$M$2:$M$6492,$A10,Source_Detail!$AD$2:$AD$6492,"Linn") -> 909 | I10: =SUMIFS(Source_Detail!$T$2:$T$6492,Source_Detail!$M$2:$M$6492,$A10,Source_Detail!$AD$2:$AD$6492,"Linn") -> 559439 | J10: =IFERROR(D10/C10,"N/M") -> 1.0511996 | K10: =IFERROR(C10/B10,"N/M") -> 0.044490204 | L10: =IFERROR(F10/E10,"N/M") -> 0.20712085 | M10: =IFERROR(D10/F10,"N/M") -> 31156.947 | O10: =SUMIFS(Source_Detail!$V$2:$V$6492,Source_Detail!$M$2:$M$6492,$A10,Source_Detail!$AD$2:$AD$6492,"Iowa ex-Linn") -> 33274253305 | P10: =SUMIFS(Source_Detail!$W$2:$W$6492,Source_Detail!$M$2:$M$6492,$A10,Source_Detail!$AD$2:$AD$6492,"Iowa ex-Linn") -> 1906841393 | Q10: =SUMIFS(Source_Detail!$AB$2:$AB$6492,Source_Detail!$M$2:$M$6492,$A10,Source_Detail!$AD$2:$AD$6492,"Iowa ex-Linn") -> 756855592 | R10: =SUMIFS(Source_Detail!$O$2:$O$6492,Source_Detail!$M$2:$M$6492,$A10,Source_Detail!$AD$2:$AD$6492,"Iowa ex-Linn") -> 229543 | S10: =SUMIFS(Source_Detail!$P$2:$P$6492,Source_Detail!$M$2:$M$6492,$A10,Source_Detail!$AD$2:$AD$6492,"Iowa ex-Linn") -> 38942 | T10: =SUMIFS(Source_Detail!$Q$2:$Q$6492,Source_Detail!$M$2:$M$6492,$A10,Source_Detail!$AD$2:$AD$6492,"Iowa ex-Linn") -> 361759 | U10: =SUMIFS(Source_Detail!$R$2:$R$6492,Source_Detail!$M$2:$M$6492,$A10,Source_Detail!$AD$2:$AD$6492,"Iowa ex-Linn") -> 53438 | V10: =SUMIFS(Source_Detail!$T$2:$T$6492,Source_Detail!$M$2:$M$6492,$A10,Source_Detail!$AD$2:$AD$6492,"Iowa ex-Linn") -> 46864388 | W10: =IFERROR(Q10/P10,"N/M") -> 0.39691586 | X10: =IFERROR(P10/O10,"N/M") -> 0.057306812 | Y10: =IFERROR(S10/R10,"N/M") -> 0.16965013 | Z10: =IFERROR(Q10/S10,"N/M") -> 19435.458
A11: 0.85 | B11: =SUMIFS(Source_Detail!$V$2:$V$6492,Source_Detail!$M$2:$M$6492,$A11,Source_Detail!$AD$2:$AD$6492,"Linn") -> 514260012 | C11: =SUMIFS(Source_Detail!$W$2:$W$6492,Source_Detail!$M$2:$M$6492,$A11,Source_Detail!$AD$2:$AD$6492,"Linn") -> 28431238 | D11: =SUMIFS(Source_Detail!$AB$2:$AB$6492,Source_Detail!$M$2:$M$6492,$A11,Source_Detail!$AD$2:$AD$6492,"Linn") -> 26159254 | E11: =SUMIFS(Source_Detail!$O$2:$O$6492,Source_Detail!$M$2:$M$6492,$A11,Source_Detail!$AD$2:$AD$6492,"Linn") -> 3235 | F11: =SUMIFS(Source_Detail!$P$2:$P$6492,Source_Detail!$M$2:$M$6492,$A11,Source_Detail!$AD$2:$AD$6492,"Linn") -> 688 | G11: =SUMIFS(Source_Detail!$Q$2:$Q$6492,Source_Detail!$M$2:$M$6492,$A11,Source_Detail!$AD$2:$AD$6492,"Linn") -> 4916 | H11: =SUMIFS(Source_Detail!$R$2:$R$6492,Source_Detail!$M$2:$M$6492,$A11,Source_Detail!$AD$2:$AD$6492,"Linn") -> 991 | I11: =SUMIFS(Source_Detail!$T$2:$T$6492,Source_Detail!$M$2:$M$6492,$A11,Source_Detail!$AD$2:$AD$6492,"Linn") -> 688283 | J11: =IFERROR(D11/C11,"N/M") -> 0.92008846 | K11: =IFERROR(C11/B11,"N/M") -> 0.055285726 | L11: =IFERROR(F11/E11,"N/M") -> 0.21267388 | M11: =IFERROR(D11/F11,"N/M") -> 38022.172 | O11: =SUMIFS(Source_Detail!$V$2:$V$6492,Source_Detail!$M$2:$M$6492,$A11,Source_Detail!$AD$2:$AD$6492,"Iowa ex-Linn") -> 39545745872 | P11: =SUMIFS(Source_Detail!$W$2:$W$6492,Source_Detail!$M$2:$M$6492,$A11,Source_Detail!$AD$2:$AD$6492,"Iowa ex-Linn") -> 2542099262 | Q11: =SUMIFS(Source_Detail!$AB$2:$AB$6492,Source_Detail!$M$2:$M$6492,$A11,Source_Detail!$AD$2:$AD$6492,"Iowa ex-Linn") -> 1292764092 | R11: =SUMIFS(Source_Detail!$O$2:$O$6492,Source_Detail!$M$2:$M$6492,$A11,Source_Detail!$AD$2:$AD$6492,"Iowa ex-Linn") -> 223094 | S11: =SUMIFS(Source_Detail!$P$2:$P$6492,Source_Detail!$M$2:$M$6492,$A11,Source_Detail!$AD$2:$AD$6492,"Iowa ex-Linn") -> 53747 | T11: =SUMIFS(Source_Detail!$Q$2:$Q$6492,Source_Detail!$M$2:$M$6492,$A11,Source_Detail!$AD$2:$AD$6492,"Iowa ex-Linn") -> 395241 | U11: =SUMIFS(Source_Detail!$R$2:$R$6492,Source_Detail!$M$2:$M$6492,$A11,Source_Detail!$AD$2:$AD$6492,"Iowa ex-Linn") -> 81174 | V11: =SUMIFS(Source_Detail!$T$2:$T$6492,Source_Detail!$M$2:$M$6492,$A11,Source_Detail!$AD$2:$AD$6492,"Iowa ex-Linn") -> 52568535 | W11: =IFERROR(Q11/P11,"N/M") -> 0.50854194 | X11: =IFERROR(P11/O11,"N/M") -> 0.064282496 | Y11: =IFERROR(S11/R11,"N/M") -> 0.24091639 | Z11: =IFERROR(Q11/S11,"N/M") -> 24052.767
A14: Interpretation note
A15: Linn has no earned exposure at 60% and only 2, 12, and 58 earned units at 50%, 55%, and 65%, respectively. Those cells remain visible as N/M or thin experience; they are context, not evidence that the lower coverage levels are safer. The indication is therefore selected on the pooled 50%–85% county experience rather than separate level indications.

Sheet Source_Detail
A1: Source File | B1: Commodity Year | C1: State Code | D1: State | E1: County Code | F1: County Name | G1: Commodity Code | H1: Commodity Name | I1: Plan Code | J1: Plan | K1: Coverage Category | L1: Delivery Type | M1: Coverage Level | N1: Policies Sold | O1: Policies Earning Premium | P1: Policies Indemnified | Q1: Units Earning Premium | R1: Units Indemnified | S1: Quantity Type | T1: Net Reported Quantity | U1: Endorsed/Companion Acres | V1: Liability | W1: Total Premium | X1: Subsidy | Y1: State/Private Subsidy | Z1: Additional Subsidy | AA1: EFA Premium Discount | AB1: Indemnity | AC1: Source Loss Ratio | AD1: Scope | AE1: Recalculated Loss Ratio | AF1: Record Key | AG1: Eligibility
A2: sobcov_2015.zip | B2: 2015 | C2: 19 | D2: IA | E2: 1 | F2: Adair | G2: 41 | H2: CORN | I2: 2 | J2: RP | K2: A | L2: RBUP | M2: 0.6 | N2: 1 | O2: 1 | P2: 0 | Q2: 1 | R2: 0 | S2: Acres | T2: 63 | U2: 0 | V2: 22602 | W2: 543 | X2: 348 | Y2: 0 | Z2: 0 | AA2: 0 | AB2: 0 | AC2: 0 | AD2: =IF(E2=113,"Linn","Iowa ex-Linn") -> Iowa ex-Linn | AE2: =IFERROR(AB2/W2,"N/M") -> 0 | AF2: =B2&"|"&TEXT(E2,"000")&"|"&TEXT(M2,"0.0000") -> 2015|001|0.6000 | AG2: =IF(AND(B2>=2015,B2<=2024,C2=19,G2=41,I2=2,K2="A",L2="RBUP",M2>=0.5,M2<=0.85),"IN","OUT") -> IN
A3: sobcov_2015.zip | B3: 2015 | C3: 19 | D3: IA | E3: 1 | F3: Adair | G3: 41 | H3: CORN | I3: 2 | J3: RP | K3: A | L3: RBUP | M3: 0.65 | N3: 15 | O3: 12 | P3: 0 | Q3: 27 | R3: 0 | S3: Acres | T3: 1914 | U3: 0 | V3: 780810 | W3: 21261 | X3: 13628 | Y3: 0 | Z3: 0 | AA3: 0 | AB3: 0 | AC3: 0 | AD3: =IF(E3=113,"Linn","Iowa ex-Linn") -> Iowa ex-Linn | AE3: =IFERROR(AB3/W3,"N/M") -> 0 | AF3: =B3&"|"&TEXT(E3,"000")&"|"&TEXT(M3,"0.0000") -> 2015|001|0.6500 | AG3: =IF(AND(B3>=2015,B3<=2024,C3=19,G3=41,I3=2,K3="A",L3="RBUP",M3>=0.5,M3<=0.85),"IN","OUT") -> IN
A4: sobcov_2015.zip | B4: 2015 | C4: 19 | D4: IA | E4: 1 | F4: Adair | G4: 41 | H4: CORN | I4: 2 | J4: RP | K4: A | L4: RBUP | M4: 0.7 | N4: 39 | O4: 23 | P4: 0 | Q4: 33 | R4: 0 | S4: Acres | T4: 2128 | U4: 0 | V4: 986574 | W4: 29472 | X4: 19730 | Y4: 0 | Z4: 0 | AA4: 0 | AB4: 0 | AC4: 0 | AD4: =IF(E4=113,"Linn","Iowa ex-Linn") -> Iowa ex-Linn | AE4: =IFERROR(AB4/W4,"N/M") -> 0 | AF4: =B4&"|"&TEXT(E4,"000")&"|"&TEXT(M4,"0.0000") -> 2015|001|0.7000 | AG4: =IF(AND(B4>=2015,B4<=2024,C4=19,G4=41,I4=2,K4="A",L4="RBUP",M4>=0.5,M4<=0.85),"IN","OUT") -> IN
A5: sobcov_2015.zip | B5: 2015 | C5: 19 | D5: IA | E5: 1 | F5: Adair | G5: 41 | H5: CORN | I5: 2 | J5: RP | K5: A | L5: RBUP | M5: 0.75 | N5: 97 | O5: 75 | P5: 6 | Q5: 106 | R5: 7 | S5: Acres | T5: 12869 | U5: 0 | V5: 6592897 | W5: 293285 | X5: 205075 | Y5: 0 | Z5: 0 | AA5: 0 | AB5: 28169 | AC5: 0.1 | AD5: =IF(E5=113,"Linn","Iowa ex-Linn") -> Iowa ex-Linn | AE5: =IFERROR(AB5/W5,"N/M") -> 0.096046508 | AF5: =B5&"|"&TEXT(E5,"000")&"|"&TEXT(M5,"0.0000") -> 2015|001|0.7500 | AG5: =IF(AND(B5>=2015,B5<=2024,C5=19,G5=41,I5=2,K5="A",L5="RBUP",M5>=0.5,M5<=0.85),"IN","OUT") -> IN
A6: sobcov_2015.zip | B6: 2015 | C6: 19 | D6: IA | E6: 1 | F6: Adair | G6: 41 | H6: CORN | I6: 2 | J6: RP | K6: A | L6: RBUP | M6: 0.8 | N6: 276 | O6: 237 | P6: 10 | Q6: 332 | R6: 15 | S6: Acres | T6: 47575 | U6: 0 | V6: 26351666 | W6: 1477390 | X6: 924845 | Y6: 0 | Z6: 0 | AA6: 0 | AB6: 83009 | AC6: 0.06 | AD6: =IF(E6=113,"Linn","Iowa ex-Linn") -> Iowa ex-Linn | AE6: =IFERROR(AB6/W6,"N/M") -> 0.056186247 | AF6: =B6&"|"&TEXT(E6,"000")&"|"&TEXT(M6,"0.0000") -> 2015|001|0.8000 | AG6: =IF(AND(B6>=2015,B6<=2024,C6=19,G6=41,I6=2,K6="A",L6="RBUP",M6>=0.5,M6<=0.85),"IN","OUT") -> IN
A7: sobcov_2015.zip | B7: 2015 | C7: 19 | D7: IA | E7: 1 | F7: Adair | G7: 41 | H7: CORN | I7: 2 | J7: RP | K7: A | L7: RBUP | M7: 0.85 | N7: 219 | O7: 172 | P7: 29 | Q7: 259 | R7: 60 | S7: Acres | T7: 38614 | U7: 0 | V7: 22333100 | W7: 1533938 | X7: 730901 | Y7: 0 | Z7: 0 | AA7: 0 | AB7: 1229981 | AC7: 0.8 | AD7: =IF(E7=113,"Linn","Iowa ex-Linn") -> Iowa ex-Linn | AE7: =IFERROR(AB7/W7,"N/M") -> 0.80184532 | AF7: =B7&"|"&TEXT(E7,"000")&"|"&TEXT(M7,"0.0000") -> 2015|001|0.8500 | AG7: =IF(AND(B7>=2015,B7<=2024,C7=19,G7=41,I7=2,K7="A",L7="RBUP",M7>=0.5,M7<=0.85),"IN","OUT") -> IN
A8: sobcov_2015.zip | B8: 2015 | C8: 19 | D8: IA | E8: 3 | F8: Adams | G8: 41 | H8: CORN | I8: 2 | J8: RP | K8: A | L8: RBUP | M8: 0.5 | N8: 1 | O8: 0 | P8: 0 | Q8: 0 | R8: 0 | S8: Acres | T8: 0 | U8: 0 | V8: 0 | W8: 0 | X8: 0 | Y8: 0 | Z8: 0 | AA8: 0 | AB8: 0 | AC8: 0 | AD8: =IF(E8=113,"Linn","Iowa ex-Linn") -> Iowa ex-Linn | AE8: =IFERROR(AB8/W8,"N/M") -> N/M | AF8: =B8&"|"&TEXT(E8,"000")&"|"&TEXT(M8,"0.0000") -> 2015|003|0.5000 | AG8: =IF(AND(B8>=2015,B8<=2024,C8=19,G8=41,I8=2,K8="A",L8="RBUP",M8>=0.5,M8<=0.85),"IN","OUT") -> IN
A9: sobcov_2015.zip | B9: 2015 | C9: 19 | D9: IA | E9: 3 | F9: Adams | G9: 41 | H9: CORN | I9: 2 | J9: RP | K9: A | L9: RBUP | M9: 0.55 | N9: 1 | O9: 0 | P9: 0 | Q9: 0 | R9: 0 | S9: Acres | T9: 0 | U9: 0 | V9: 0 | W9: 0 | X9: 0 | Y9: 0 | Z9: 0 | AA9: 0 | AB9: 0 | AC9: 0 | AD9: =IF(E9=113,"Linn","Iowa ex-Linn") -> Iowa ex-Linn | AE9: =IFERROR(AB9/W9,"N/M") -> N/M | AF9: =B9&"|"&TEXT(E9,"000")&"|"&TEXT(M9,"0.0000") -> 2015|003|0.5500 | AG9: =IF(AND(B9>=2015,B9<=2024,C9=19,G9=41,I9=2,K9="A",L9="RBUP",M9>=0.5,M9<=0.85),"IN","OUT") -> IN
A10: sobcov_2015.zip | B10: 2015 | C10: 19 | D10: IA | E10: 3 | F10: Adams | G10: 41 | H10: CORN | I10: 2 | J10: RP | K10: A | L10: RBUP | M10: 0.6 | N10: 1 | O10: 1 | P10: 0 | Q10: 1 | R10: 0 | S10: Acres | T10: 57 | U10: 0 | V10: 24498 | W10: 494 | X10: 316 | Y10: 0 | Z10: 0 | AA10: 0 | AB10: 0 | AC10: 0 | AD10: =IF(E10=113,"Linn","Iowa ex-Linn") -> Iowa ex-Linn | AE10: =IFERROR(AB10/W10,"N/M") -> 0 | AF10: =B10&"|"&TEXT(E10,"000")&"|"&TEXT(M10,"0.0000") -> 2015|003|0.6000 | AG10: =IF(AND(B10>=2015,B10<=2024,C10=19,G10=41,I10=2,K10="A",L10="RBUP",M10>=0.5,M10<=0.85),"IN","OUT") -> IN
A11: sobcov_2015.zip | B11: 2015 | C11: 19 | D11: IA | E11: 3 | F11: Adams | G11: 41 | H11: CORN | I11: 2 | J11: RP | K11: A | L11: RBUP | M11: 0.65 | N11: 9 | O11: 8 | P11: 0 | Q11: 10 | R11: 0 | S11: Acres | T11: 457 | U11: 0 | V11: 197242 | W11: 6807 | X11: 4017 | Y11: 0 | Z11: 0 | AA11: 0 | AB11: 0 | AC11: 0 | AD11: =IF(E11=113,"Linn","Iowa ex-Linn") -> Iowa ex-Linn | AE11: =IFERROR(AB11/W11,"N/M") -> 0 | AF11: =B11&"|"&TEXT(E11,"000")&"|"&TEXT(M11,"0.0000") -> 2015|003|0.6500 | AG11: =IF(AND(B11>=2015,B11<=2024,C11=19,G11=41,I11=2,K11="A",L11="RBUP",M11>=0.5,M11<=0.85),"IN","OUT") -> IN
A12: sobcov_2015.zip | B12: 2015 | C12: 19 | D12: IA | E12: 3 | F12: Adams | G12: 41 | H12: CORN | I12: 2 | J12: RP | K12: A | L12: RBUP | M12: 0.7 | N12: 32 | O12: 25 | P12: 2 | Q12: 36 | R12: 3 | S12: Acres | T12: 3706 | U12: 0 | V12: 1737381 | W12: 83135 | X12: 58113 | Y12: 0 | Z12: 0 | AA12: 0 | AB12: 12921 | AC12: 0.16 | AD12: =IF(E12=113,"Linn","Iowa ex-Linn") -> Iowa ex-Linn | AE12: =IFERROR(AB12/W12,"N/M") -> 0.1554219 | AF12: =B12&"|"&TEXT(E12,"000")&"|"&TEXT(M12,"0.0000") -> 2015|003|0.7000 | AG12: =IF(AND(B12>=2015,B12<=2024,C12=19,G12=41,I12=2,K12="A",L12="RBUP",M12>=0.5,M12<=0.85),"IN","OUT") -> IN
A13: sobcov_2015.zip | B13: 2015 | C13: 19 | D13: IA | E13: 3 | F13: Adams | G13: 41 | H13: CORN | I13: 2 | J13: RP | K13: A | L13: RBUP | M13: 0.75 | N13: 117 | O13: 89 | P13: 12 | Q13: 117 | R13: 15 | S13: Acres | T13: 12322 | U13: 0 | V13: 6206710 | W13: 382553 | X13: 258494 | Y13: 0 | Z13: 0 | AA13: 0 | AB13: 105123 | AC13: 0.27 | AD13: =IF(E13=113,"Linn","Iowa ex-Linn") -> Iowa ex-Linn | AE13: =IFERROR(AB13/W13,"N/M") -> 0.2747933 | AF13: =B13&"|"&TEXT(E13,"000")&"|"&TEXT(M13,"0.0000") -> 2015|003|0.7500 | AG13: =IF(AND(B13>=2015,B13<=2024,C13=19,G13=41,I13=2,K13="A",L13="RBUP",M13>=0.5,M13<=0.85),"IN","OUT") -> IN
... A6492: sobcov_2024.zip | B6492: 2024 | C6492: 19 | D6492: IA | E6492: 197 | F6492: Wright | G6492: 41 | H6492: Corn | I6492: 2 | J6492: RP | K6492: A | L6492: RBUP | M6492: 0.85 | N6492: 403 | O6492: 339 | P6492: 185 | Q6492: 720 | R6492: 337 | S6492: Acres | T6492: 96164 | U6492: 0 | V6492: 77201886 | W6492: 4531109 | X6492: 2022729 | Y6492: 3200 | Z6492: 0 | AA6492: 0 | AB6492: 3210665 | AC6492: 0.71 | AD6492: =IF(E6492=113,"Linn","Iowa ex-Linn") -> Iowa ex-Linn | AE6492: =IFERROR(AB6492/W6492,"N/M") -> 0.7085826 | AF6492: =B6492&"|"&TEXT(E6492,"000")&"|"&TEXT(M6492,"0.0000") -> 2024|197|0.8500 | AG6492: =IF(AND(B6492>=2015,B6492<=2024,C6492=19,G6492=41,I6492=2,K6492="A",L6492="RBUP",M6492>=0.5,M6492<=0.85),"IN","OUT") -> IN

Sheet Controls
A1: Control checks | source to indication
A2: Each status compares the computed actual value with the stated expected value
A3: Control | B3: Formula / test | C3: Actual | D3: Expected | E3: Status
A4: Filtered source rows | B4: COUNTA source file | C4: =COUNTA(Source_Detail!$A$2:$A$6492) -> 6491 | D4: 6491 | E4: =IF(C4=D4,"PASS","FAIL") -> PASS
A5: Linn source rows | B5: COUNTIF scope | C5: =COUNTIF(Source_Detail!$AD$2:$AD$6492,"Linn") -> 55 | D5: 55 | E5: =IF(C5=D5,"PASS","FAIL") -> PASS
A6: Iowa ex-Linn source rows | B6: COUNTIF scope | C6: =COUNTIF(Source_Detail!$AD$2:$AD$6492,"Iowa ex-Linn") -> 6436 | D6: 6436 | E6: =IF(C6=D6,"PASS","FAIL") -> PASS
A7: Minimum commodity year | B7: MIN detail year | C7: =MIN(Source_Detail!$B$2:$B$6492) -> 2015 | D7: 2015 | E7: =IF(C7=D7,"PASS","FAIL") -> PASS
A8: Maximum commodity year | B8: MAX detail year | C8: =MAX(Source_Detail!$B$2:$B$6492) -> 2024 | D8: 2024 | E8: =IF(C8=D8,"PASS","FAIL") -> PASS
A9: Out-of-scope state rows | B9: State code <> 19 | C9: =COUNTIF(Source_Detail!$C$2:$C$6492,"<>19") -> 0 | D9: 0 | E9: =IF(C9=D9,"PASS","FAIL") -> PASS
A10: Out-of-scope commodity rows | B10: Commodity code <> 41 | C10: =COUNTIF(Source_Detail!$G$2:$G$6492,"<>41") -> 0 | D10: 0 | E10: =IF(C10=D10,"PASS","FAIL") -> PASS | F10: Overall control status | G10: =IF(COUNTIF(E4:E22,"FAIL")+COUNTIF(F26:F35,"FAIL")=0,"PASS","FAIL") -> PASS
A11: Out-of-scope plan rows | B11: Plan code <> 2 | C11: =COUNTIF(Source_Detail!$I$2:$I$6492,"<>2") -> 0 | D11: 0 | E11: =IF(C11=D11,"PASS","FAIL") -> PASS
A12: Out-of-scope category rows | B12: Coverage category <> A | C12: =COUNTIF(Source_Detail!$K$2:$K$6492,"<>A") -> 0 | D12: 0 | E12: =IF(C12=D12,"PASS","FAIL") -> PASS
A13: Out-of-scope delivery rows | B13: Delivery type <> RBUP | C13: =COUNTIF(Source_Detail!$L$2:$L$6492,"<>RBUP") -> 0 | D13: 0 | E13: =IF(C13=D13,"PASS","FAIL") -> PASS
A14: Coverage outside 50%–85% | B14: COUNTIFS lower + upper | C14: =COUNTIF(Source_Detail!$M$2:$M$6492,"<0.5")+COUNTIF(Source_Detail!$M$2:$M$6492,">0.85") -> 0 | D14: 0 | E14: =IF(C14=D14,"PASS","FAIL") -> PASS
A15: Eligibility formula OUT rows | B15: COUNTIF live scope flag | C15: =COUNTIF(Source_Detail!$AG$2:$AG$6492,"OUT") -> 0 | D15: 0 | E15: =IF(C15=D15,"PASS","FAIL") -> PASS
A16: Duplicate year/county/level keys | B16: COUNTIF key > 1 | C16: =SUMPRODUCT(--(COUNTIF(Source_Detail!$AF$2:$AF$6492,Source_Detail!$AF$2:$AF$6492)>1)) -> 0 | D16: 0 | E16: =IF(C16=D16,"PASS","FAIL") -> PASS
A17: Linn decade base premium | B17: SUM annual experience | C17: =SUM(Annual_Experience!$C$4:$C$13) -> 48899058 | D17: 48899058 | E17: =IF(C17=D17,"PASS","FAIL") -> PASS
A18: Linn decade indemnity | B18: SUM annual experience | C18: =SUM(Annual_Experience!$D$4:$D$13) -> 47945371 | D18: 47945371 | E18: =IF(C18=D18,"PASS","FAIL") -> PASS
A19: Iowa ex-Linn base premium | B19: SUM annual experience | C19: =SUM(Annual_Experience!$P$4:$P$13) -> 5051186245 | D19: 5051186245 | E19: =IF(C19=D19,"PASS","FAIL") -> PASS
A20: Iowa ex-Linn indemnity | B20: SUM annual experience | C20: =SUM(Annual_Experience!$Q$4:$Q$13) -> 2237759108 | D20: 2237759108 | E20: =IF(C20=D20,"PASS","FAIL") -> PASS
A21: Linn annual/detail premium difference | B21: Annual less source SUMIF | C21: =SUM(Annual_Experience!$C$4:$C$13)-SUMIF(Source_Detail!$AD$2:$AD$6492,"Linn",Source_Detail!$W$2:$W$6492) -> 0 | D21: 0 | E21: =IF(C21=D21,"PASS","FAIL") -> PASS
A22: Complement annual/detail indemnity difference | B22: Annual less source SUMIF | C22: =SUM(Annual_Experience!$Q$4:$Q$13)-SUMIF(Source_Detail!$AD$2:$AD$6492,"Iowa ex-Linn",Source_Detail!$AB$2:$AB$6492) -> 0 | D22: 0 | E22: =IF(C22=D22,"PASS","FAIL") -> PASS
A24: Frozen source-file inventory | 11 supplied files
A25: File | B25: Internal member | C25: National rows | D25: Filtered rows | E25: Actual filtered | F25: Status | G25: SHA-256 | H25: RMA URL
A26: sobcov_2015.zip | B26: sobcov15.txt | C26: 134391 | D26: 623 | E26: =COUNTIF(Source_Detail!$A$2:$A$6492,A26) -> 623 | F26: =IF(D26=E26,"PASS","FAIL") -> PASS | G26: e331a07433b278b31588a6274753ea57f2387bb5654ca14a9723676d108b349e | H26: RMA archive
A27: sobcov_2016.zip | B27: sobcov_2016.txt | C27: 134258 | D27: 634 | E27: =COUNTIF(Source_Detail!$A$2:$A$6492,A27) -> 634 | F27: =IF(D27=E27,"PASS","FAIL") -> PASS | G27: a7b37a94d979a6be52c048c2c4326baad370504953944cccf9b2720e4f9d022f | H27: RMA archive
A28: sobcov_2017.zip | B28: sobcov_2017.txt | C28: 133865 | D28: 650 | E28: =COUNTIF(Source_Detail!$A$2:$A$6492,A28) -> 650 | F28: =IF(D28=E28,"PASS","FAIL") -> PASS | G28: 692d10bd0a00e67b2baf772c1a2ba6e3d5c10b8085f81677ae430a495847c543 | H28: RMA archive
A29: sobcov_2018.zip | B29: sobcov_2018.txt | C29: 135367 | D29: 666 | E29: =COUNTIF(Source_Detail!$A$2:$A$6492,A29) -> 666 | F29: =IF(D29=E29,"PASS","FAIL") -> PASS | G29: 383df0942103b66ec6d742c6c8e3c7118f42d136ea57ba6ceb231f9d77f9e210 | H29: RMA archive
A30: sobcov_2019.zip | B30: sobcov_2019.txt | C30: 139856 | D30: 669 | E30: =COUNTIF(Source_Detail!$A$2:$A$6492,A30) -> 669 | F30: =IF(D30=E30,"PASS","FAIL") -> PASS | G30: 5a45243145abbbdde55a7b80641a0e9edfb9242142096c4354833ecf31b42636 | H30: RMA archive
A31: sobcov_2020.zip | B31: sobcov_2020.txt | C31: 141784 | D31: 659 | E31: =COUNTIF(Source_Detail!$A$2:$A$6492,A31) -> 659 | F31: =IF(D31=E31,"PASS","FAIL") -> PASS | G31: bb63824b45785d8e1fb0b39baaa689ca9f24ab1e71001242d3b9cc33611b341d | H31: RMA archive
A32: sobcov_2021.zip | B32: sobcov_2021.txt | C32: 147893 | D32: 646 | E32: =COUNTIF(Source_Detail!$A$2:$A$6492,A32) -> 646 | F32: =IF(D32=E32,"PASS","FAIL") -> PASS | G32: d11918586b45be1109ba20ae0dfb0814c66b107385c04f58414cc47c83a7e792 | H32: RMA archive
A33: sobcov_2022.zip | B33: sobcov_2022.txt | C33: 149928 | D33: 656 | E33: =COUNTIF(Source_Detail!$A$2:$A$6492,A33) -> 656 | F33: =IF(D33=E33,"PASS","FAIL") -> PASS | G33: 5f7e24a128387caf4727cf9e23a01e65f3525e2e7f263d876842a0a0eee86620 | H33: RMA archive
A34: sobcov_2023.zip | B34: sobcov_2023.txt | C34: 153011 | D34: 650 | E34: =COUNTIF(Source_Detail!$A$2:$A$6492,A34) -> 650 | F34: =IF(D34=E34,"PASS","FAIL") -> PASS | G34: 56bb19f4ac3c1395439e90b6df6d16504d50365d0bc80af8d19be2e133271e3a | H34: RMA archive
A35: sobcov_2024.zip | B35: sobcov_2024.txt | C35: 152383 | D35: 638 | E35: =COUNTIF(Source_Detail!$A$2:$A$6492,A35) -> 638 | F35: =IF(D35=E35,"PASS","FAIL") -> PASS | G35: aa61e08c6792fa0a472b5a0fe3b6ca52087eec8b57e48c54f4a6f5d7f7dddf99 | H35: RMA archive
A36: SOB_State_County_Crop_with_Coverage_Level_1989_Forward.pdf | G36: fd62972c8219e1e6cb90c4b1ae2f7ad3ada3e759c12c007b2b379da55e606307 | H36: RMA layout PDF

Sheet Definitions
A1: Sources, definitions, and methods
A2: Field meaning follows the supplied RMA 1989-forward record layout; source files supplied with this task were treated as the frozen record.
A4: Scope and method register
A5: Item | B5: Workbook treatment | D5: Reason / source
A6: Scope | B6: 2015–2024; IA 19; Linn 113; corn 0041; RP 02; A; RBUP; coverage .5000–.8500 | D6: Task scope; RMA codes are retained in Source_Detail.
A7: Complement | B7: All in-scope Iowa rows with county code other than 113 | D7: Excludes Linn to avoid overlap in the credibility complement.
A8: Text | B8: Trim leading and trailing padding | D8: Source is fixed-width text within pipe-delimited fields.
A9: Dollars | B9: Nominal dollars; Total Premium is pre-subsidy base premium | D9: RMA layout definition for element 22.
A10: Loss ratio | B10: SUM(Indemnity) / SUM(Total Premium) | D10: Never averages the two-decimal source loss-ratio field.
A11: Rate on liability | B11: SUM(Total Premium) / SUM(Liability) | D11: Premium rate proxy for the selected scope.
A12: Policy claim frequency | B12: SUM(Policies Indemnified) / SUM(Policies Earning Premium) | D12: Count-based frequency at the policy level.
A13: Severity | B13: SUM(Indemnity) / SUM(Policies Indemnified) | D13: Nominal dollars per indemnified policy.
A14: Horizon selection | B14: 20% × 2022–2024 LR + 30% × 2020–2024 LR + 50% × 2015–2024 LR | D14: Portfolio planning standard supplied in the assignment.
A15: Credibility | B15: MIN(1, SQRT(Linn 10-year units earning premium / 40,000)) | D15: Square-root credibility with the supplied full-credibility standard.
A16: Selected LR | B16: Z × Linn horizon selection + (1−Z) × Iowa ex-Linn horizon selection | D16: Non-overlapping geographic complement.
... A18: Zero denominators | B18: Shown as N/M | D18: A zero denominator is not presented as a 0% outcome.
A21: RMA field definitions
A22: Element | B22: Field | C22: Definition | D22: PDF page | E22: Workbook column | F22: Use in analysis
A23: 1 | B23: Commodity Year | C23: Year in which the commodity is normally harvested; the policy year for which coverage was provided. | D23: 1 | E23: B | F23: Direct
A24: 2 | B24: Location State Code | C24: FIPS code for the state in which the insured farm is located. | D24: 1 | E24: C | F24: Direct
A25: 3 | B25: Location State Abbreviation | C25: USPS state abbreviation. | D25: 1 | E25: D | F25: Retained
A26: 4 | B26: Location County Code | C26: FIPS code for the county in which the insured farm is located. | D26: 1 | E26: E | F26: Direct
A27: 5 | B27: Location County Name | C27: County name. | D27: 1 | E27: F | F27: Retained
A28: 6 | B28: Commodity Code | C28: RMA code for the insured crop or commodity. | D28: 1 | E28: G | F28: Direct
A29: 7 | B29: Commodity Name | C29: Name of the insured crop or commodity. | D29: 1 | E29: H | F29: Retained
A30: 8 | B30: Insurance Plan Code | C30: Code for the selected type of insurance coverage. | D30: 1 | E30: I | F30: Direct
A31: 9 | B31: Insurance Plan Name Abbreviation | C31: Abbreviation of the insurance plan name. | D31: 1 | E31: J | F31: Retained
A32: 10 | B32: Coverage Category | C32: Coverage election: A=Buyup; C=CAT; E=Existing Coverage Policy; L=Limited Coverage. | D32: 1 | E32: K | F32: Direct
A33: 11 | B33: Delivery Type | C33: RBUP is reinsured buyup coverage; other layout values include RCAT, FCAT, and FBUP. | D33: 1 | E33: L | F33: Direct
A34: 12 | B34: Coverage Level | C34: Elected coverage expressed as a decimal; its complement is the deductible. | D34: 1 | E34: M | F34: Direct
... A50: 28 | B50: Loss Ratio | C50: Indemnity divided by Total Premium; supplied at two-decimal precision. | D50: 3 | E50: AC | F50: Direct
